Workbook

Sheet Users
A1: ID | B1: ชื่อผู้ใช้ | C1: email | D1: role
A3: 40866b4e | B3: Administrator | C3: serviceticket222@gmail.com | D3: admin
A5: ca8ec9c2 | B5: OnIn | C5: it@dwellled.com | D5: admin
A6: 2089f2b1 | B6: film | C6: nattharikachumnan@gmail.com | D6: admin
A7: 57899c30 | B7: พี่เอ็กซ์ | C7: marketing@dwellled.com | D7: admin
A8: f3619cab | B8: พี่เปา | C8: dr.sales1@dr-ads.com | D8: admin
A9: 1645650e | B9: พี่บอย | C9: serviceteam.ad3@gmail.com | D9: admin

Sheet รายงาน

Sheet Detail233-Samsung-รับเรื่อง
A1: ID | B1: Ref. | C1: แหล่งที่มา | D1: วันเวลาที่รับแจ้ง | E1: เลขที่ติดตามงาน | F1: ลูกค้า | G1: สถานที่/สาขา | H1: สถานที่ตั้ง | I1: ผู้ติดต่อ | J1: เบอร์ติดต่อ | K1: ข้อมูลการรับแจ้ง | L1: รูปภาพที่แจ้ง | M1: MA | N1: ลักษณะงาน | O1: สถานะงาน | P1: ผู้ดำเนินการ | Q1: วันที่นัดหมาย เวลาเริ่มต้น | R1: วันที่นัดหมาย เวลาสิ้นสุด | S1: รายละเอียดการดำเนินการ | T1: ผลการดำเนินการ | U1: เกี่ยวกับอุปกรณ์ | V1: รูปภาพที่ดำเนินการเสร็จแล้ว | W1: วันเวลาเสร็จ | X1: MAP | Y1: วัน/ชั่วโมงที่ใช้ | Z1: ทะเบียนรถ | AA1: หมายเหตุ | AB1: ไฟล์
A2: b6ef2a7f | C2: ไลน์ | D2: 45693.396 | E2: SAM001041 | F2: Samsung | G2: PARAGON | K2: จอร้าน SAMSUNG PARAGON แจ้งจอเม็ดเสียครับ | L2: DataServiceDR_Images/b6ef2a7f.รูปภาพที่แจ้ง.023108.jpg | N2: แก้ไขหน้างาน | O2: รับเรื่อง | W2: 45693.396 | Y2: 0 วัน 0 ชั่วโมง

Sheet Detail228-American Eagle-กำลังด
A1: ID | B1: Ref. | C1: แหล่งที่มา | D1: วันเวลาที่รับแจ้ง | E1: เลขที่ติดตามงาน | F1: ลูกค้า | G1: สถานที่/สาขา | H1: สถานที่ตั้ง | I1: ผู้ติดต่อ | J1: เบอร์ติดต่อ | K1: ข้อมูลการรับแจ้ง | L1: รูปภาพที่แจ้ง | M1: MA | N1: ลักษณะงาน | O1: สถานะงาน | P1: ผู้ดำเนินการ | Q1: วันที่นัดหมาย เวลาเริ่มต้น | R1: วันที่นัดหมาย เวลาสิ้นสุด | S1: รายละเอียดการดำเนินการ | T1: ผลการดำเนินการ | U1: เกี่ยวกับอุปกรณ์ | V1: รูปภาพที่ดำเนินการเสร็จแล้ว | W1: วันเวลาเสร็จ | X1: MAP | Y1: วัน/ชั่วโมงที่ใช้ | Z1: ทะเบียนรถ | AA1: หมายเหตุ | AB1: ไฟล์
A2: cede76a6 | C2: อีเมล์ | D2: 45596.607 | E2: AME000429 | F2: American Eagle | G2: เดอะมอลล์ บางแค | I2: คุณทราย | K2: แบรนด์ AMERICAN EAGLE สาขา เดอะมอลล์ บางแค ***รบกวนอัพโหลดวีดีโอตาม link ด้านล่าง ตามวันที่ที่แจ้งไว้ค่ะ*** In store promotion สำหรับวันที่ 1 - 4 Nov 2024 Link : https://drive.google.com/drive/u/0/folders/1xaOE3PWI99S2JNib7Ru_7WJgxsbAplYP | M2: TRUE | N2: รีโมท | O2: กำลังดำเนินการ | P2: โมชิ | Q2: 45597.615 | R2: 45597.615 | S2: อัพเดตสื่อ | U2: อัพเดทสื่อ | W2: 45596.607 | Y2: 0 วัน 0 ชั่วโมง
A3: d42cc0fc | C3: อีเมล์ | D3: 45596.609 | E3: AME000430 | F3: American Eagle | G3: เดอะมอลล์ บางแค | I3: คุณทราย | K3: In store promotion สำหรับวันที่ 5 - 8 Nov 2024 *** ขอให้ขึ้นวีดีโอภายใน 10 โมง ไม่เลท รบกวนด้วยนะคะ Link : https://drive.google.com/drive/u/0/folders/1QAeyZlRwrxd-prfBRgiXr1Ml_YkK21X_ | M3: TRUE | N3: รีโมท | O3: กำลังดำเนินการ | P3: โมชิ | Q3: 45601.615 | R3: 45601.615 | S3: อัพสื่อ | U3: อัพเดทสื่อ | W3: 45596.609 | Y3: 0 วัน 0 ชั่วโมง
A4: 784c87fe | C4: อีเมล์ | D4: 45596.61 | E4: AME000431 | F4: American Eagle | G4: เดอะมอลล์ บางแค | I4: คุณทราย | K4: In store promotion สำหรับวันที่ 9 - 10 Nov 2024 Link : https://drive.google.com/drive/u/0/folders/1xaOE3PWI99S2JNib7Ru_7WJgxsbAplYP | M4: TRUE | N4: รีโมท | O4: กำลังดำเนินการ | P4: โมชิ | Q4: 45605.612 | R4: 45605.612 | S4: อัพสื่อใหม่ | U4: อัพเดทสื่อ | W4: 45596.61 | Y4: 0 วัน 0 ชั่วโมง
A5: 62094db3 | C5: ไลน์ | D5: 45596.714 | E5: AME000433 | F5: American Eagle | G5: เซ็นทรัลเวิลด์ CTW | I5: คุณทราย | K5: จอไม่ออนไลน์ในระบบ | M5: TRUE | N5: แก้ไขหน้างาน | O5: กำลังดำเนินการ | P5: สนุ๊ก | R5: 45596.737 | S5: เข้าเชื่อมไวไฟ และดึงเข้าระบบ | W5: 45596.714 | Y5: 0 วัน 0 ชั่วโมง

Sheet DataServiceDR
A1: ID | B1: Ref. | C1: แหล่งที่มา | D1: วันเวลาที่รับแจ้ง | E1: เลขที่ติดตามงาน | F1: ลูกค้า | G1: สถานที่/สาขา | H1: สถานที่ตั้ง | I1: ผู้ติดต่อ | J1: เบอร์ติดต่อ | K1: ข้อมูลการรับแจ้ง | L1: รูปภาพที่แจ้ง | M1: MA | N1: ลักษณะงาน | O1: สถานะงาน | P1: ผู้ดำเนินการ | Q1: วันที่นัดหมาย เวลาเริ่มต้น | R1: วันที่นัดหมาย เวลาสิ้นสุด | S1: รายละเอียดการดำเนินการ | T1: ผลการดำเนินการ | U1: เกี่ยวกับอุปกรณ์ | V1: รูปภาพที่ดำเนินการเสร็จแล้ว | W1: วันเวลาเสร็จ | X1: MAP | Y1: วัน/ชั่วโมงที่ใช้ | Z1: ทะเบียนรถ | AA1: หมายเหตุ | AB1: ไฟล์
A2: 1 | C2: ไลน์ | D2: 45533.476 | E2: =UPPER(LEFT(F2,3))&TEXT(COUNTA($F$2:F2),"000000") -> BMN000001 | F2: BMN | G2: ด่านเก็บค่าผ่านทางพิเศษ ด่านสาทร | K2: แผ่นโมดูลสีเพี้ยน | M2: NO | N2: แก้ไขหน้างาน | O2: เรียบร้อยปกติ | P2: โมชิ | U2: Module | W2: 45535.917 | Y2: =ROUND(IF(ISBLANK(W2), (NOW() - D2) * 24 / 24, (W2 - D2) * 24 / 24), 2) & " วัน " & ROUND(MOD(IF(ISBLANK(W2), (NOW() - D2) * 24, (W2 - D2) * 24), 24), 2) & " ชั่วโมง" -> 2.44 วัน 10.57 ชั่วโมง
A3: 2 | C3: ไลน์ | D3: 45533.476 | E3: =UPPER(LEFT(F3,3))&TEXT(COUNTA($F$2:F3),"000000") -> BMN000002 | F3: BMN | G3: ด่านเก็บค่าผ่านทางพิเศษ ด่านสาทร | K3: แผ่นโมดูลสีเพี้ยน | M3: NO | N3: แก้ไขหน้างาน | O3: เรียบร้อยปกติ | P3: โมชิ | S3: รบกวนทำใบเสนอราคา 1.ช่าง 2.แผ่นโมดู | T3: เปลี่ยนแผ่นโมดูล 1 แผ่น | U3: Module | W3: 45535.917 | Y3: =ROUND(IF(ISBLANK(W3), (NOW() - D3) * 24 / 24, (W3 - D3) * 24 / 24), 2) & " วัน " & ROUND(MOD(IF(ISBLANK(W3), (NOW() - D3) * 24, (W3 - D3) * 24), 24), 2) & " ชั่วโมง" -> 2.44 วัน 10.57 ชั่วโมง
A4: 3 | C4: ไลน์ | D4: 45547 | E4: =UPPER(LEFT(F4,3))&TEXT(COUNTA($F$2:F4),"000000") -> BMN000003 | F4: BMN | G4: ด่านเก็บค่าผ่านทางพิเศษ ด่านอโศก 3 | K4: จอดับทุกจอ | M4: YES | N4: แก้ไขหน้างาน | O4: เรียบร้อยปกติ | S4: ฟิวส์ขาด | T4: เปลี่ี่ยนฟิวส์ | U4: Sending | W4: 45538.604 | Y4: =ROUND(IF(ISBLANK(W4), (NOW() - D4) * 24 / 24, (W4 - D4) * 24 / 24), 2) & " วัน " & ROUND(MOD(IF(ISBLANK(W4), (NOW() - D4) * 24, (W4 - D4) * 24), 24), 2) & " ชั่วโมง" -> -8.4 วัน 14.5 ชั่วโมง
A5: 4 | C5: ไลน์ | D5: 45540.466 | E5: =UPPER(LEFT(F5,3))&TEXT(COUNTA($F$2:F5),"000000") -> BMN000004 | F5: BMN | G5: ด่านประชาชื่นขาออก | K5: จอดับทุกจอ | M5: YES | N5: แก้ไขหน้างาน | O5: เรียบร้อยปกติ | S5: ตรวจสอบหัวแลนไม่มีสัญญาณ | T5: ย้ำหัวแลนใหม่ | U5: Sending | W5: 45540.667 | Y5: =ROUND(IF(ISBLANK(W5), (NOW() - D5) * 24 / 24, (W5 - D5) * 24 / 24), 2) & " วัน " & ROUND(MOD(IF(ISBLANK(W5), (NOW() - D5) * 24, (W5 - D5) * 24), 24), 2) & " ชั่วโมง" -> 0.2 วัน 4.82 ชั่วโมง
A6: 5 | C6: ไลน์ | D6: 45543.36 | E6: =UPPER(LEFT(F6,3))&TEXT(COUNTA($F$2:F6),"000000") -> BMN000005 | F6: BMN | G6: ด่านเก็บค่าผ่านทางพิเศษ ด่านอโศก 3 | K6: จอดับทุกจอ | M6: YES | N6: แก้ไขหน้างาน | O6: เรียบร้อยปกติ | S6: โปรเซสเซอร์ขึ้น No input ตรวจสอบพบ Player ดับ | T6: ทำการเสียบปลั๊กใหม่ | U6: Sending | W6: 45543.601 | Y6: =ROUND(IF(ISBLANK(W6), (NOW() - D6) * 24 / 24, (W6 - D6) * 24 / 24), 2) & " วัน " & ROUND(MOD(IF(ISBLANK(W6), (NOW() - D6) * 24, (W6 - D6) * 24), 24), 2) & " ชั่วโมง" -> 0.24 วัน 5.77 ชั่วโมง | AA6: 1. เดินทางมาถึงพบว่าจอติดปกติ (ทีมไวร์เออมาถึงก่อน) 2.สอบถามทีมไวร์เออ แจ้งว่า โปรเซสเซอร์ขึ้น No input ตรวจสอบแล้ว playerดับ เปิดplayer จอติดปกติครับ
A7: 6 | C7: ไลน์ | D7: 45472 | E7: =UPPER(LEFT(F7,3))&TEXT(COUNTA($F$2:F7),"000000") -> BMN000006 | F7: BMN | G7: สถานีจตุจักร จอ Column ฝั่ง NE | K7: แจ้งซ่อมจอสื่อ สถานีสวนจตุจักร(BL13)ดับ 1จุด ขั้นออกบัตรโดยสาร หน้าห้องSOR ทางออกประตู1,4 ครับ | M7: YES | N7: แก้ไขหน้างาน | O7: เรียบร้อยปกติ | P7: เหน่ง, เคี้ยง | S7: เข้าแก้ไขจอกล่อง Digital Column แผ่นโมตูลดับบางส่วน | T7: เปลี่ยนการ์ด 1 จุด เปลี่ยนสายlen 1 เส้น | U7: Recive | W7: 45544.562 | Y7: =ROUND(IF(ISBLANK(W7), (NOW() - D7) * 24 / 24, (W7 - D7) * 24 / 24), 2) & " วัน " & ROUND(MOD(IF(ISBLANK(W7), (NOW() - D7) * 24, (W7 - D7) * 24), 24), 2) & " ชั่วโมง" -> 72.56 วัน 13.5 ชั่วโมง | AA7: เข้าครั้งที่1. MANPOWER : เหน่ง กร ทะเบียนรถ : 3221 วันเวลาเริ่ม : 29/6/2024 13.00 น. วันเวลาเสร็จ : 1/7/2024 16.00 น. ผลการตรวจสอบ : 1.ตรวจวัด กระแสV ได้ 8.1V (หม้อแปลงเสีย) 2.เปลี่ยนหม้อแปลง 350-5V 1ใบ 3.เปิดจอแล้วแผ่นยังไม่ติด 4.ทดลองสลับการ์ดแล้วไม่ติด 5.นำสายแพรไปเสียบการ์ดตัวอื่นติด 6.นำสายแพรแผ่นที่ติดมาเสียบการ์ดที่เปลี่ยนหม้อแปลงผลปรากฏว่าแผ่นไม่ติด วิธีแก้ไข : ไม่สามารถแก้ไขได้ครับ ผู้ติดต่อ : >ช่างแก้ไขระบุ เบอร์โทร : >ช่างแก้ไขระบุ สถานะแก้ไข : Process ------------------------------------- เข้าครั้งที่2. งาน : แก้ไข กลุ่มบริษัทลูกค้า : BMN วันเวลานัดหมาย : 1/7/2024 15:00-16:00 สถานที่ : เซนทรัลชิดลม ที่สถานีจตุจักร บริเวณ Concourse ฝั่ง NE ข้อมูลการรับแจ้ง : เแผ่นโมดูลดับบางส่วน ##################################### MANPOWER : พี่จ่อย,สาวหยาง ทะเบียนรถ : 3221 วันเวลาเริ่ม : 1/7/2024 13.00 น. วันเวลาเสร็จ : 1/7/2024 16.00 น. ผลการตรวจสอบ : พบการ์ดเสีย 1 ใบ และสายแลนเสีย 1 เส้น วิธีแก้ไข : เปลี่ยนการ์ด 1 จุด เปลี่ยนสายlen 1 เส้น ผู้ติดต่อ : >ช่างแก้ไขระบุ เบอร์โทร : >ช่างแก้ไขระบุ สถานะแก้ไข : Close หมายเหตุ : พิกัด : แนบรูปหน้างาน
A8: 7 | C8: ไลน์ | D8: 45473.625 | E8: =UPPER(LEFT(F8,3))&TEXT(COUNTA($F$2:F8),"000000") -> BMN000007 | F8: BMN | G8: MRT เพชรบุรี | K8: แก้ไขกล่องไฟไดนามิกดับ3กล่อง | M8: YES | N8: แก้ไขหน้างาน | O8: เรียบร้อยปกติ | P8: เหน่ง, เคี้ยง | S8: สาเหตุลูกค้าปิดสวิทย์คันโยกทั้ง3กล่อง | T8: ทำการยกสวิทย์คันโยกเครื่องใช้งานได้ปกติ | U8: Sending | W8: 45474.625 | Y8: =ROUND(IF(ISBLANK(W8), (NOW() - D8) * 24 / 24, (W8 - D8) * 24 / 24), 2) & " วัน " & ROUND(MOD(IF(ISBLANK(W8), (NOW() - D8) * 24, (W8 - D8) * 24), 24), 2) & " ชั่วโมง" -> 1 วัน 0 ชั่วโมง
A9: 8 | C9: ไลน์ | D9: 45474.475 | E9: =UPPER(LEFT(F9,3))&TEXT(COUNTA($F$2:F9),"000000") -> BMN000008 | F9: BMN | G9: สถานีเพชรบุรี จอColumn ด้านหลังจอ Wellcome | K9: จอไดนามิกดับ | M9: YES | N9: แก้ไขหน้างาน | O9: เรียบร้อยปกติ | P9: วิรชน สมร_จ่อย | S9: สายไฟ DC เสีย 1 เส้น | T9: ทำการเเก้ใขเปลี่ยนสายDCใหม่ 1 เส้น | U9: Sending | W9: 45474.667 | Y9: =ROUND(IF(ISBLANK(W9), (NOW() - D9) * 24 / 24, (W9 - D9) * 24 / 24), 2) & " วัน " & ROUND(MOD(IF(ISBLANK(W9), (NOW() - D9) * 24, (W9 - D9) * 24), 24), 2) & " ชั่วโมง" -> 0.19 วัน 4.6 ชั่วโมง
A10: 9 | C10: ไลน์ | D10: 45474 | E10: =UPPER(LEFT(F10,3))&TEXT(COUNTA($F$2:F10),"000000") -> BMN000009 | F10: BMN | G10: ตอม่อแยกประดิพัพท์ | K10: จอ LED มีแผ่นโมดูลดับ 1 แผ่น | M10: YES | N10: แก้ไขหน้างาน | O10: เรียบร้อยปกติ | P10: ส่าวหย่าง | S10: แผ่นโมดูลเสีย จำนวน 1 แผ่น | T10: เปลี่ยนแผ่นใหม่จำนวน 1 แผ่น | U10: Module | W10: 45474.667 | Y10: =ROUND(IF(ISBLANK(W10), (NOW() - D10) * 24 / 24, (W10 - D10) * 24 / 24), 2) & " วัน " & ROUND(MOD(IF(ISBLANK(W10), (NOW() - D10) * 24, (W10 - D10) * 24), 24), 2) & " ชั่วโมง" -> 0.67 วัน 16 ชั่วโมง
A11: 10 | C11: ไลน์ | D11: 45545 | E11: =UPPER(LEFT(F11,3))&TEXT(COUNTA($F$2:F11),"000000") -> RIC000010 | F11: Ricco | G11: Adidas เซ็นทรัล พัทยา | K11: ฝากเปลี่ยนสื่อในอีกโปรแกรม จอ 21.5นิ้ว สาขา CRC Pattaya ให้หน่อย ครับ เล่นแทนสื่อเก่า เปลี่ยนได้เลยครับ | M11: YES | N11: รีโมท | O11: เรียบร้อยปกติ | P11: ฟลุ๊ค | S11: อัพสื่อ | T11: อัพสื่อเรียบร้อย | U11: Sending | W11: 45545.674 | Y11: =ROUND(IF(ISBLANK(W11), (NOW() - D11) * 24 / 24, (W11 - D11) * 24 / 24), 2) & " วัน " & ROUND(MOD(IF(ISBLANK(W11), (NOW() - D11) * 24, (W11 - D11) * 24), 24), 2) & " ชั่วโมง" -> 0.67 วัน 16.17 ชั่วโมง
A12: 11 | C12: ไลน์ | D12: 45537 | E12: =UPPER(LEFT(F12,3))&TEXT(COUNTA($F$2:F12),"000000") -> VES000011 | F12: Vespa | G12: เวสป้าบางแค | K12: เปลี่ยนจอ Kiosk | M12: YES | N12: แก้ไขหน้างาน | O12: เรียบร้อยปกติ | P12: หนูเล็ก | S12: เปลี่ยนจอ Kiosk 43นิ้ว ทัช จำนวน 1 จอ โดยเปลี่ยนใช้ Box เดิมของหน้าสาขา | T12: เปลี่ยนจอ Kiosk 43นิ้ว ทัช จำนวน 1 จอ โดยเปลี่ยนใช้ Box เดิมของหน้าสาขา | U12: Panel | W12: 45537.611 | Y12: =ROUND(IF(ISBLANK(W12), (NOW() - D12) * 24 / 24, (W12 - D12) * 24 / 24), 2) & " วัน " & ROUND(MOD(IF(ISBLANK(W12), (NOW() - D12) * 24, (W12 - D12) * 24), 24), 2) & " ชั่วโมง" -> 0.61 วัน 14.67 ชั่วโมง
A13: 12 | C13: ไลน์ | D13: 45537 | E13: =UPPER(LEFT(F13,3))&TEXT(COUNTA($F$2:F13),"000000") -> WOR000012 | F13: Workzone | G13: Workzone | K13: ส่งจอ Monitor 32นิ้ว จำนวน 2 จอ Monitor 21.5 นิ้ว= 2 จอ | M13: YES | N13: แก้ไขหน้างาน | O13: เรียบร้อยปกติ | P13: ณัฐวุฒิ อรรถประจง_โอ๋ | S13: ส่งจอ Monitor 32นิ้ว จำนวน 2 จอ Monitor 21.5 นิ้ว= 2 จอ | T13: Qc จอกับลูกเรียบร้อยเเละส่งครับ | U13: Panel | W13: 45537.642 | Y13: =ROUND(IF(ISBLANK(W13), (NOW() - D13) * 24 / 24, (W13 - D13) * 24 / 24), 2) & " วัน " & ROUND(MOD(IF(ISBLANK(W13), (NOW() - D13) * 24, (W13 - D13) * 24), 24), 2) & " ชั่วโมง" -> 0.64 วัน 15.42 ชั่วโมง
A14: 13 | C14: ไลน์ | D14: 45534 | E14: =UPPER(LEFT(F14,3))&TEXT(COUNTA($F$2:F14),"000000") -> EVE000013 | F14: EVEANDBOY | G14: เมเจอร์ ปิ่นเกล้า | K14: ติดตั้งจอล้อมเสา | M14: YES | N14: แก้ไขหน้างาน | O14: เรียบร้อยปกติ | P14: ณัฐวุฒิ อรรถประจง_โอ๋ | S14: ติดตั้งจอล้อมเสา | T14: เรียบร้อย | U14: Module | W14: 45537.708 | Y14: =ROUND(IF(ISBLANK(W14), (NOW() - D14) * 24 / 24, (W14 - D14) * 24 / 24), 2) & " วัน " & ROUND(MOD(IF(ISBLANK(W14), (NOW() - D14) * 24, (W14 - D14) * 24), 24), 2) & " ชั่วโมง" -> 3.71 วัน 17 ชั่วโมง
A15: 14 | B15: 7304563 | C15: ไลน์ | D15: 45532.495 | E15: =UPPER(LEFT(F15,3))&TEXT(COUNTA($F$2:F15),"000000") -> TRU000014 | F15: TRUE | G15: True Shop Central Plaza Udonthani | I15: พลอยไพลิน | J15: 0966466694 | K15: จอดับบางส่วน | M15: YES | N15: รีโมท | O15: เรียบร้อยปกติ | P15: ปรีชา ภูตานันท์_ชาสลิม, ชินาธิป สุขรูป_เณน | S15: เกิดจากการกล่องควบคุมจอค้าง | T15: สั่ง ปิด เปิด กล่องผ่านระบบ online ให้ลูกค้าใหม่ | U15: Module | W15: 45532.495 | Y15: =ROUND(IF(ISBLANK(W15), (NOW() - D15) * 24 / 24, (W15 - D15) * 24 / 24), 2) & " วัน " & ROUND(MOD(IF(ISBLANK(W15), (NOW() - D15) * 24, (W15 - D15) * 24), 24), 2) & " ชั่วโมง" -> 0 วัน 0 ชั่วโมง | AB15: TR0013
A16: 15 | B16: 7309348 | C16: ไลน์ | D16: 45531.538 | E16: =UPPER(LEFT(F16,3))&TEXT(COUNTA($F$2:F16),"000000") -> TRU000015 | F16: TRUE | G16: True Shop Central Chanthaburi | I16: แคทรียา | J16: 0839789897 | K16: สื่อไม่อัพเดทสาขายังพบปัญหาจอสลับเหมือนเดิม | M16: YES | N16: รีโมท | O16: เรียบร้อยปกติ | P16: โมชิ | S16: เกิดจากการขึ้นสื่อผิดจอขิงทีมขึ้นสื่อเนื่องจากเป็นการเพิ่มสินค้าภายหลัง ทำให้การระบุจอ ซ้าย ขวา กลางผิดพลาด | T16: สลับสื่อขึ้นจอให้ลูกค้าใหม่ | U16: แก้ไขสื่อ | W16: 45531.538 | Y16: =ROUND(IF(ISBLANK(W16), (NOW() - D16) * 24 / 24, (W16 - D16) * 24 / 24), 2) & " วัน " & ROUND(MOD(IF(ISBLANK(W16), (NOW() - D16) * 24, (W16 - D16) * 24), 24), 2) & " ชั่วโมง" -> 0 วัน 0 ชั่วโมง | AB16: TR0014
A17: 16 | B17: 7309518 | C17: ไลน์ | D17: 45531.542 | E17: =UPPER(LEFT(F17,3))&TEXT(COUNTA($F$2:F17),"000000") -> TRU000016 | F17: TRUE | G17: True Shop Terminal 21 | I17: Chutima | J17: 0955965646 | K17: สื่อไม่อัพเดทสื่อขึ้นสลับฝั่ง | M17: YES | N17: รีโมท | O17: เรียบร้อยปกติ | P17: โมชิ | S17: เกิดจากการจัดชั้นวางสินค้าซ้าย ขวา ของทางหน้าร้าน กับทีมขึันสื่อเรา เนื่องจากไม่มีรูปประกอบ ตั้งแต่แรกที่มีแจ้งเพิ่มสินค้าในชั้นวาง | T17: สลับสื่อขึ้นจอให้ลูกค้าใหม่ | U17: แก้ไขสื่อ | W17: 45531.542 | Y17: =ROUND(IF(ISBLANK(W17), (NOW() - D17) * 24 / 24, (W17 - D17) * 24 / 24), 2) & " วัน " & ROUND(MOD(IF(ISBLANK(W17), (NOW() - D17) * 24, (W17 - D17) * 24), 24), 2) & " ชั่วโมง" -> 0 วัน 0 ชั่วโมง | AB17: TR0015
A18: 17 | B18: 7312801 | C18: ไลน์ | D18: 45536.465 | E18: =UPPER(LEFT(F18,3))&TEXT(COUNTA($F$2:F18),"000000") -> TRU000017 | F18: TRUE | G18: True Branding Shop True Tower 1 | I18: นันทวัน | J18: 0970974560 | K18: สื่อไม่อัพเดทจอทีวี Marketing สื่อไม่ขึ้น 2 จอ จอด้านซ้าย และจอกลาง รบกวนให้เจ้าหน้าที่ช่วยแก้ไขด่วนด้วยครับ | M18: YES | N18: รีโมท | O18: เรียบร้อยปกติ | P18: โมชิ | S18: เกิดจากการจัดชั้นวางสินค้าซ้าย ขวา ของทางหน้าร้าน กับทีมขึันสื่อเรา เนื่องจากไม่มีรูปประกอบ ตั้งแต่แรกที่มีแจ้งเพิ่มสินค้าในชั้นวาง | T18: สลับสื่อขึ้นจอให้ลูกค้าใหม่ | U18: แก้ไขสื่อ | W18: 45536.465 | Y18: =ROUND(IF(ISBLANK(W18), (NOW() - D18) * 24 / 24, (W18 - D18) * 24 / 24), 2) & " วัน " & ROUND(MOD(IF(ISBLANK(W18), (NOW() - D18) * 24, (W18 - D18) * 24), 24), 2) & " ชั่วโมง" -> 0 วัน 0 ชั่วโมง | AB18: TR0016
A19: 18 | B19: 7317121 | C19: ไลน์ | D19: 45536.423 | E19: =UPPER(LEFT(F19,3))&TEXT(COUNTA($F$2:F19),"000000") -> TRU000018 | F19: TRUE | G19: True Shop Central Rama 9 | I19: สุพัตรา | J19: 0842988898 | K19: จอดับบางส่วน | M19: YES | N19: รีโมท | O19: เรียบร้อยปกติ | P19: โมชิ | S19: เกิดจากการตั้งกำหนดเวลาเล่นสื่อของทีมขึ้นสื่อ คือตั้งกำหนดหมดอายุ สิ้นเดือน สิงหาคม | T19: ยกเลิกกำหนดเวลาในโปรแกรม และส่งสื่อขึ้นจอให้ใหม่ | U19: แก้ไขสื่อ | W19: 45536.423 | Y19: =ROUND(IF(ISBLANK(W19), (NOW() - D19) * 24 / 24, (W19 - D19) * 24 / 24), 2) & " วัน " & ROUND(MOD(IF(ISBLANK(W19), (NOW() - D19) * 24, (W19 - D19) * 24), 24), 2) & " ชั่วโมง" -> 0 วัน 0 ชั่วโมง | AB19: TR0017
A20: 19 | B20: 7317169 | C20: ไลน์ | D20: 45537 | E20: =UPPER(LEFT(F20,3))&TEXT(COUNTA($F$2:F20),"000000") -> TRU000019 | F20: TRUE | G20: True Shop Robinson Roiet | I20: Thanayut | J20: 0955544450 | K20: จอดับบางส่วน จอโฆษณา Accessories ดับ จอไม่แสดงสื่อโฆษณา | M20: YES | N20: รีโมท | O20: เรียบร้อยปกติ | P20: โมชิ | S20: เกิดจากการตั้งกำหนดเวลาเล่นสื่อของทีมขึ้นสื่อ คือตั้งกำหนดหมดอายุ สิ้นเดือน สิงหาคม | T20: ยกเลิกกำหนดเวลาในโปรแกรม และส่งสื่อขึ้นจอให้ใหม่ | U20: แก้ไขสื่อ | W20: 45537.423 | Y20: =ROUND(IF(ISBLANK(W20), (NOW() - D20) * 24 / 24, (W20 - D20) * 24 / 24), 2) & " วัน " & ROUND(MOD(IF(ISBLANK(W20), (NOW() - D20) * 24, (W20 - D20) * 24), 24), 2) & " ชั่วโมง" -> 0.42 วัน 10.15 ชั่วโมง | AB20: TR0018
A21: 20 | B21: 7317157 | C21: ไลน์ | D21: 45536.424 | E21: =UPPER(LEFT(F21,3))&TEXT(COUNTA($F$2:F21),"000000") -> TRU000020 | F21: TRUE | G21: True Shop Emquartier | I21: Narttaya | J21: 0956619797 | K21: จอดับบางส่วน หน้าจอเปิด ไม่ติด รบกวนหน่วยงานตรวจสอบและแก้ไข จอ ให้ด้วยค่ะ ขึ้นจอดำ | M21: YES | N21: รีโมท | O21: เรียบร้อยปกติ | P21: โมชิ | S21: เกิดจากการตั้งกำหนดเวลาเล่นสื่อของทีมขึ้นสื่อ คือตั้งกำหนดหมดอายุ สิ้นเดือน สิงหาคม | T21: ยกเลิกกำหนดเวลาในโปรแกรม และส่งสื่อขึ้นจอให้ใหม่ | U21: แก้ไขสื่อ | W21: 45536.424 | Y21: =ROUND(IF(ISBLANK(W21), (NOW() - D21) * 24 / 24, (W21 - D21) * 24 / 24), 2) & " วัน " & ROUND(MOD(IF(ISBLANK(W21), (NOW() - D21) * 24, (W21 - D21) * 24), 24), 2) & " ชั่วโมง" -> 0 วัน 0 ชั่วโมง | AB21: TR0019
A22: 21 | B22: 7317168 | C22: ไลน์ | D22: 45536.427 | E22: =UPPER(LEFT(F22,3))&TEXT(COUNTA($F$2:F22),"000000") -> TRU000021 | F22: TRUE | G22: True Shop Central Chonburi | I22: Arnont | J22: 0909042570/0918269964 | K22: จอดับบางส่วน หน้าจอเปิด ไม่ติด จอ TV Corner 3 จอเปิดไม่ติด ไม่มีสื่อ รูปภาพตามไฟล์แนบ | M22: YES | N22: รีโมท | O22: เรียบร้อยปกติ | P22: โมชิ | S22: เกิดจากการตั้งกำหนดเวลาเล่นสื่อของทีมขึ้นสื่อ คือตั้งกำหนดหมดอายุ สิ้นเดือน สิงหาคม | T22: ยกเลิกกำหนดเวลาในโปรแกรม และส่งสื่อขึ้นจอให้ใหม่ | U22: แก้ไขสื่อ | W22: 45536.427 | Y22: =ROUND(IF(ISBLANK(W22), (NOW() - D22) * 24 / 24, (W22 - D22) * 24 / 24), 2) & " วัน " & ROUND(MOD(IF(ISBLANK(W22), (NOW() - D22) * 24, (W22 - D22) * 24), 24), 2) & " ชั่วโมง" -> 0 วัน 0 ชั่วโมง | AB22: TR0020
A23: 22 | B23: 7317171 | C23: ไลน์ | D23: 45536.428 | E23: =UPPER(LEFT(F23,3))&TEXT(COUNTA($F$2:F23),"000000") -> TRU000022 | F23: TRUE | G23: True Shop Central Plaza Ramindra | I23: Chayapon | J23: 0809719995 | K23: จอดับบางส่วน หน้าจอเปิด ไม่ติด | M23: YES | N23: รีโมท | O23: เรียบร้อยปกติ | P23: โมชิ | S23: เกิดจากการตั้งกำหนดเวลาเล่นสื่อของทีมขึ้นสื่อ คือตั้งกำหนดหมดอายุ สิ้นเดือน สิงหาคม | T23: ยกเลิกกำหนดเวลาในโปรแกรม และส่งสื่อขึ้นจอให้ใหม่ | U23: แก้ไขสื่อ | W23: 45536.428 | Y23: =ROUND(IF(ISBLANK(W23), (NOW() - D23) * 24 / 24, (W23 - D23) * 24 / 24), 2) & " วัน " & ROUND(MOD(IF(ISBLANK(W23), (NOW() - D23) * 24, (W23 - D23) * 24), 24), 2) & " ชั่วโมง" -> 0 วัน 0 ชั่วโมง | AB23: TR0021
A24: 23 | B24: 7317181 | C24: ไลน์ | D24: 45536.434 | E24: =UPPER(LEFT(F24,3))&TEXT(COUNTA($F$2:F24),"000000") -> TRU000023 | F24: TRUE | G24: True Shop Central Plaza Ramindra | I24: Supapron | J24: 0955655445 | M24: YES | N24: รีโมท | O24: เรียบร้อยปกติ | P24: โมชิ | S24: เกิดจากการตั้งกำหนดเวลาเล่นสื่อของทีมขึ้นสื่อ คือตั้งกำหนดหมดอายุ สิ้นเดือน สิงหาคม | T24: ยกเลิกกำหนดเวลาในโปรแกรม และส่งสื่อขึ้นจอให้ใหม่ | U24: แก้ไขสื่อ | W24: 45536.434 | Y24: =ROUND(IF(ISBLANK(W24), (NOW() - D24) * 24 / 24, (W24 - D24) * 24 / 24), 2) & " วัน " & ROUND(MOD(IF(ISBLANK(W24), (NOW() - D24) * 24, (W24 - D24) * 24), 24), 2) & " ชั่วโมง" -> 0 วัน 0 ชั่วโมง | AB24: TR0022
A25: 24 | B25: 7317196 | C25: ไลน์ | D25: 45536.437 | E25: =UPPER(LEFT(F25,3))&TEXT(COUNTA($F$2:F25),"000000") -> TRU000024 | F25: TRUE | G25: True Branding Shop Siam Square Soi 2 | I25: กฤตวิทย์ | J25: 0645269192 | K25: สื่อไม่อัพเดทจอ TV ไม่ทำการโชว์สื่อ | M25: YES | N25: รีโมท | O25: เรียบร้อยปกติ | P25: โมชิ | S25: เกิดจากการตั้งกำหนดเวลาเล่นสื่อของทีมขึ้นสื่อ คือตั้งกำหนดหมดอายุ สิ้นเดือน สิงหาคม | T25: ยกเลิกกำหนดเวลาในโปรแกรม และส่งสื่อขึ้นจอให้ใหม่ | U25: แก้ไขสื่อ | W25: 45536.437 | Y25: =ROUND(IF(ISBLANK(W25), (NOW() - D25) * 24 / 24, (W25 - D25) * 24 / 24), 2) & " วัน " & ROUND(MOD(IF(ISBLANK(W25), (NOW() - D25) * 24, (W25 - D25) * 24), 24), 2) & " ชั่วโมง" -> 0 วัน 0 ชั่วโมง | AB25: TR0023
A26: 25 | B26: 7317230 | C26: ไลน์ | D26: 45536.444 | E26: =UPPER(LEFT(F26,3))&TEXT(COUNTA($F$2:F26),"000000") -> TRU000025 | F26: TRUE | G26: True Shop Central Plaza Udonthani | I26: ศิริขวัญ | J26: 0644199966 | K26: จอดับบางส่วน หน้าจอเปิด ไม่ติด | M26: YES | N26: รีโมท | O26: เรียบร้อยปกติ | P26: โมชิ | S26: เกิดจากการตั้งกำหนดเวลาเล่นสื่อของทีมขึ้นสื่อ คือตั้งกำหนดหมดอายุ สิ้นเดือน สิงหาคม | T26: ยกเลิกกำหนดเวลาในโปรแกรม และส่งสื่อขึ้นจอให้ใหม่ | U26: แก้ไขสื่อ | W26: 45536.444 | Y26: =ROUND(IF(ISBLANK(W26), (NOW() - D26) * 24 / 24, (W26 - D26) * 24 / 24), 2) & " วัน " & ROUND(MOD(IF(ISBLANK(W26), (NOW() - D26) * 24, (W26 - D26) * 24), 24), 2) & " ชั่วโมง" -> 0 วัน 0 ชั่วโมง | AB26: TR0024
A27: 26 | B27: 7317214 | C27: ไลน์ | D27: 45536.449 | E27: =UPPER(LEFT(F27,3))&TEXT(COUNTA($F$2:F27),"000000") -> TRU000026 | F27: TRUE | G27: True Branding Shop Central Embassy | I27: ศวิตา | J27: 0842974646 | K27: จอ ดับ2จอ ครับ | M27: YES | N27: รีโมท | O27: เรียบร้อยปกติ | P27: โมชิ | S27: เกิดจากการตั้งกำหนดเวลาเล่นสื่อของทีมขึ้นสื่อ คือตั้งกำหนดหมดอายุ สิ้นเดือน สิงหาคม | T27: ยกเลิกกำหนดเวลาในโปรแกรม และส่งสื่อขึ้นจอให้ใหม่ | U27: แก้ไขสื่อ | W27: 45536.449 | Y27: =ROUND(IF(ISBLANK(W27), (NOW() - D27) * 24 / 24, (W27 - D27) * 24 / 24), 2) & " วัน " & ROUND(MOD(IF(ISBLANK(W27), (NOW() - D27) * 24, (W27 - D27) * 24), 24), 2) & " ชั่วโมง" -> 0 วัน 0 ชั่วโมง | AB27: TR0025
A28: 27 | B28: 7317215 | C28: ไลน์ | D28: 45536.455 | E28: =UPPER(LEFT(F28,3))&TEXT(COUNTA($F$2:F28),"000000") -> TRU000027 | F28: TRUE | G28: True Shop The Mall Bangkapi | I28: Nittaya | J28: 0893545982 | K28: จอไม่โชว์สื่อ(ระบบสัญญาณ)/จอไม่ติดค่ะ ขึ้นแสดงLogo แล้วดับไป เอกสารตามไฟล์แนบ | M28: YES | N28: รีโมท | O28: เรียบร้อยปกติ | P28: โมชิ | S28: เกิดจากการตั้งกำหนดเวลาเล่นสื่อของทีมขึ้นสื่อ คือตั้งกำหนดหมดอายุ สิ้นเดือน สิงหาคม | T28: ยกเลิกกำหนดเวลาในโปรแกรม และส่งสื่อขึ้นจอให้ใหม่ | U28: แก้ไขสื่อ | W28: 45536.455 | Y28: =ROUND(IF(ISBLANK(W28), (NOW() - D28) * 24 / 24, (W28 - D28) * 24 / 24), 2) & " วัน " & ROUND(MOD(IF(ISBLANK(W28), (NOW() - D28) * 24, (W28 - D28) * 24), 24), 2) & " ชั่วโมง" -> 0 วัน 0 ชั่วโมง | AB28: TR0026
A29: 28 | B29: 7318459 | C29: ไลน์ | D29: 45537.387 | E29: =UPPER(LEFT(F29,3))&TEXT(COUNTA($F$2:F29),"000000") -> TRU000028 | F29: TRUE | G29: True Shop Central Nakhonsawan | I29: สุรศักดิ์ | J29: 0858333337 | K29: เนื่องจากทางสาขามีการติดตั้ง wall samsung ใหม่ รบกวน หน่วยงาน แก้ไข สื่อช่อง ตามแจ้ง เป็น samsung | M29: YES | N29: รีโมท | O29: เรียบร้อยปกติ | P29: โมชิ | S29: เกิดจากการตั้งกำหนดเวลาเล่นสื่อของทีมขึ้นสื่อ คือตั้งกำหนดหมดอายุ สิ้นเดือน สิงหาคม | T29: ยกเลิกกำหนดเวลาในโปรแกรม และส่งสื่อขึ้นจอให้ใหม่ | U29: แก้ไขสื่อ | W29: 45537.387 | Y29: =ROUND(IF(ISBLANK(W29), (NOW() - D29) * 24 / 24, (W29 - D29) * 24 / 24), 2) & " วัน " & ROUND(MOD(IF(ISBLANK(W29), (NOW() - D29) * 24, (W29 - D29) * 24), 24), 2) & " ชั่วโมง" -> 0 วัน 0 ชั่วโมง | AB29: TR0027
A30: 29 | B30: 7329061 | C30: ไลน์ | D30: 45539.503 | E30: =UPPER(LEFT(F30,3))&TEXT(COUNTA($F$2:F30),"000000") -> TRU000029 | F30: TRUE | G30: True Shop Central Chanthaburi | I30: Nitipat | J30: 0830748330 | K30: ต้องการให้สลับหน้าจอ Wall มาให้ตรงกับ Wall Samsung | M30: YES | N30: รีโมท | O30: เรียบร้อยปกติ | P30: โมชิ | S30: เกิดจากการจัดชั้นวางสินค้าซ้าย ขวา ของทางหน้าร้าน กับทีมขึันสื่อเรา เนื่องจากไม่มีรูปประกอบ ตั้งแต่แรกที่มีแจ้งเพิ่มสินค้าในชั้นวาง | T30: สลับสื่อขึ้นจอให้ลูกค้าใหม่ | U30: แก้ไขสื่อ | W30: 45539.503 | Y30: =ROUND(IF(ISBLANK(W30), (NOW() - D30) * 24 / 24, (W30 - D30) * 24 / 24), 2) & " วัน " & ROUND(MOD(IF(ISBLANK(W30), (NOW() - D30) * 24, (W30 - D30) * 24), 24), 2) & " ชั่วโมง" -> 0 วัน 0 ชั่วโมง | AB30: TR0028
A31: 30 | B31: 7329317 | C31: ไลน์ | D31: 45541.535 | E31: =UPPER(LEFT(F31,3))&TEXT(COUNTA($F$2:F31),"000000") -> TRU000030 | F31: TRUE | G31: True Shop Seacon Square 2 | I31: Chutima | J31: 0955965646 | K31: จอ สื่ออัพเดทสลับกัน | M31: YES | N31: รีโมท | O31: เรียบร้อยปกติ | P31: โมชิ | S31: เกิดจากการจัดชั้นวางสินค้าซ้าย ขวา ของทางหน้าร้าน กับทีมขึันสื่อเรา เนื่องจากไม่มีรูปประกอบ ตั้งแต่แรกที่มีแจ้งเพิ่มสินค้าในชั้นวาง | T31: สลับสื่อขึ้นจอให้ลูกค้าใหม่ | U31: แก้ไขสื่อ | W31: 45541.535 | Y31: =ROUND(IF(ISBLANK(W31), (NOW() - D31) * 24 / 24, (W31 - D31) * 24 / 24), 2) & " วัน " & ROUND(MOD(IF(ISBLANK(W31), (NOW() - D31) * 24, (W31 - D31) * 24), 24), 2) & " ชั่วโมง" -> 0 วัน 0 ชั่วโมง | AB31: TR0029
A32: 31 | B32: 7331177 | C32: ไลน์ | D32: 45542.511 | E32: =UPPER(LEFT(F32,3))&TEXT(COUNTA($F$2:F32),"000000") -> TRU000031 | F32: TRUE | G32: True Shop Central Festival Samui | I32: Pornchanok | J32: 0653632157 / 0956619797 | K32: จอดับบางส่วน | M32: YES | N32: รีโมท | O32: เรียบร้อยปกติ | P32: โมชิ | S32: เกิดจากการอ่านทำความเข้าใจของทีมขึ้นสื่อเราเข้าใจผิด เลยทำให้ขึ้นสื่อผิดพลาด รบกวนอัพเดทสื่อเฉพาะ baseud ให้แก่สาขาด้วย | T32: อัพเดตสื่อขึ้นจอให้ลูกค้าใหม่ | U32: แก้ไขสื่อ | W32: 45542.511 | Y32: =ROUND(IF(ISBLANK(W32), (NOW() - D32) * 24 / 24, (W32 - D32) * 24 / 24), 2) & " วัน " & ROUND(MOD(IF(ISBLANK(W32), (NOW() - D32) * 24, (W32 - D32) * 24), 24), 2) & " ชั่วโมง" -> 0 วัน 0 ชั่วโมง | AB32: TR0030
A33: 32 | C33: ไลน์ | D33: 45546.681 | E33: =UPPER(LEFT(F33,3))&TEXT(COUNTA($F$2:F33),"000000") -> TRU000032 | F33: TRUE | G33: True Shop Central Nakhonsawan | K33: สื่อ 5G Cash Back ไม่ขึ้น รบกวนดำเนินการตรวจสอบ | M33: YES | N33: รีโมท | O33: เรียบร้อยปกติ | P33: โมชิ | S33: เกิดจากการตกหล่นในการส่งขึ้นสื่อ | T33: อัพเดตสื่อขึ้นจอให้ลูกค้าใหม่ | U33: แก้ไขสื่อ | W33: 45546.701 | Y33: =ROUND(IF(ISBLANK(W33), (NOW() - D33) * 24 / 24, (W33 - D33) * 24 / 24), 2) & " วัน " & ROUND(MOD(IF(ISBLANK(W33), (NOW() - D33) * 24, (W33 - D33) * 24), 24), 2) & " ชั่วโมง" -> 0.02 วัน 0.5 ชั่วโมง
A34: 33 | C34: ไลน์ | D34: 45546.681 | E34: =UPPER(LEFT(F34,3))&TEXT(COUNTA($F$2:F34),"000000") -> TRU000033 | F34: TRUE | G34: True Shop Central mahachai | K34: สื่อ 5G Cash Back ไม่ขึ้น รบกวนดำเนินการตรวจสอบ | M34: YES | N34: รีโมท | O34: เรียบร้อยปกติ | P34: โมชิ | S34: เกิดจากการตกหล่นในการส่งขึ้นสื่อ | T34: อัพเดตสื่อขึ้นจอให้ลูกค้าใหม่ | U34: แก้ไขสื่อ | W34: 45546.701 | Y34: =ROUND(IF(ISBLANK(W34), (NOW() - D34) * 24 / 24, (W34 - D34) * 24 / 24), 2) & " วัน " & ROUND(MOD(IF(ISBLANK(W34), (NOW() - D34) * 24, (W34 - D34) * 24), 24), 2) & " ชั่วโมง" -> 0.02 วัน 0.5 ชั่วโมง
A35: 34 | B35: 7338421 | C35: ไลน์ | D35: 45546.681 | E35: =UPPER(LEFT(F35,3))&TEXT(COUNTA($F$2:F35),"000000") -> TRU000034 | F35: TRUE | G35: True Shop Central Plaza Ramindra | I35: Chayapon | J35: 0809719995 | K35: สื่อ 5G Cash Back ไม่ขึ้น รบกวนดำเนินการตรวจสอบ | M35: YES | N35: รีโมท | O35: เรียบร้อยปกติ | P35: โมชิ | S35: เกิดจากการตกหล่นในการส่งขึ้นสื่อ | T35: อัพเดตสื่อขึ้นจอให้ลูกค้าใหม่ | U35: แก้ไขสื่อ | W35: 45546.701 | Y35: =ROUND(IF(ISBLANK(W35), (NOW() - D35) * 24 / 24, (W35 - D35) * 24 / 24), 2) & " วัน " & ROUND(MOD(IF(ISBLANK(W35), (NOW() - D35) * 24, (W35 - D35) * 24), 24), 2) & " ชั่วโมง" -> 0.02 วัน 0.5 ชั่วโมง
A36: 35 | B36: 7338555 | C36: ไลน์ | D36: 45546.681 | E36: =UPPER(LEFT(F36,3))&TEXT(COUNTA($F$2:F36),"000000") -> TRU000035 | F36: TRUE | G36: True Shop Ayudhaya Park | I36: พลลภัตม์ | J36: 0840184148 | K36: สื่อ 5G Cash Back ไม่ขึ้น รบกวนดำเนินการตรวจสอบ | M36: YES | N36: รีโมท | O36: เรียบร้อยปกติ | P36: โมชิ | S36: เกิดจากการตกหล่นในการส่งขึ้นสื่อ | T36: อัพเดตสื่อขึ้นจอให้ลูกค้าใหม่ | U36: แก้ไขสื่อ | W36: 45546.701 | Y36: =ROUND(IF(ISBLANK(W36), (NOW() - D36) * 24 / 24, (W36 - D36) * 24 / 24), 2) & " วัน " & ROUND(MOD(IF(ISBLANK(W36), (NOW() - D36) * 24, (W36 - D36) * 24), 24), 2) & " ชั่วโมง" -> 0.02 วัน 0.5 ชั่วโมง
A37: 36 | B37: 7338559 | C37: ไลน์ | D37: 45546.681 | E37: =UPPER(LEFT(F37,3))&TEXT(COUNTA($F$2:F37),"000000") -> TRU000036 | F37: TRUE | G37: True Shop Imperial World Samrong | I37: Sudarat | J37: 0955959399 | K37: สื่อ 5G Cash Back ไม่ขึ้น รบกวนดำเนินการตรวจสอบ | M37: YES | N37: รีโมท | O37: เรียบร้อยปกติ | P37: โมชิ | S37: เกิดจากอาการจอกล่องควบคุมจอค้าง | T37: รีสตาร์ทกล่อง Imperial World Samrong จอติดเรียบร้อย | U37: แก้ไขสื่อ | W37: 45546.701 | Y37: =ROUND(IF(ISBLANK(W37), (NOW() - D37) * 24 / 24, (W37 - D37) * 24 / 24), 2) & " วัน " & ROUND(MOD(IF(ISBLANK(W37), (NOW() - D37) * 24, (W37 - D37) * 24), 24), 2) & " ชั่วโมง" -> 0.02 วัน 0.5 ชั่วโมง
A38: 37 | B38: 7338576 | C38: ไลน์ | D38: 45546.681 | E38: =UPPER(LEFT(F38,3))&TEXT(COUNTA($F$2:F38),"000000") -> TRU000037 | F38: TRUE | G38: True Shop Central Westville | I38: กนกลักษณ์ | J38: 0647895971 | K38: สื่อ 5G Cash Back ไม่ขึ้น รบกวนดำเนินการตรวจสอบ | M38: YES | N38: รีโมท | O38: เรียบร้อยปกติ | P38: โมชิ | S38: เกิดจากการตกหล่นในการส่งขึ้นสื่อ | T38: อัพเดตสื่อขึ้นจอให้ลูกค้าใหม่ | U38: แก้ไขสื่อ | W38: 45546.701 | Y38: =ROUND(IF(ISBLANK(W38), (NOW() - D38) * 24 / 24, (W38 - D38) * 24 / 24), 2) & " วัน " & ROUND(MOD(IF(ISBLANK(W38), (NOW() - D38) * 24, (W38 - D38) * 24), 24), 2) & " ชั่วโมง" -> 0.02 วัน 0.5 ชั่วโมง
A39: 38 | C39: ไลน์ | D39: 45546.701 | E39: =UPPER(LEFT(F39,3))&TEXT(COUNTA($F$2:F39),"000000") -> NEW000038 | F39: Newlook | G39: Adidas เซ็นทรัลปิ่นเกล้า | K39: จอดับบางส่วน | M39: YES | N39: แก้ไขหน้างาน | O39: เรียบร้อยปกติ | P39: โมชิ | S39: Recive มีปัญหา | T39: ทำการเปลี่ยน Card Recive และทำการย้ำหัวสายแลนใหม่ ทั้งหัวท้าย | U39: Recive | W39: 45558.533 | Y39: =ROUND(IF(ISBLANK(W39), (NOW() - D39) * 24 / 24, (W39 - D39) * 24 / 24), 2) & " วัน " & ROUND(MOD(IF(ISBLANK(W39), (NOW() - D39) * 24, (W39 - D39) * 24), 24), 2) & " ชั่วโมง" -> 11.83 วัน 19.95 ชั่วโมง | AB39: NE0037
A40: 39 | C40: ไลน์ | D40: 45534 | E40: =UPPER(LEFT(F40,3))&TEXT(COUNTA($F$2:F40),"000000") -> TRU000039 | F40: TRUE | G40: True Shop Central Westville | K40: สื่อ 5G Cash Back ไม่ขึ้น รบกวนดำเนินการตรวจสอบ | M40: YES | N40: รีโมท | O40: เรียบร้อยปกติ | P40: โมชิ | S40: เกิดจากการตกหล่นในการส่งขึ้นสื่อ | T40: อัพเดตสื่อขึ้นจอให้ลูกค้าใหม่ | U40: แก้ไขสื่อ | W40: 45546.681 | Y40: =ROUND(IF(ISBLANK(W40), (NOW() - D40) * 24 / 24, (W40 - D40) * 24 / 24), 2) & " วัน " & ROUND(MOD(IF(ISBLANK(W40), (NOW() - D40) * 24, (W40 - D40) * 24), 24), 2) & " ชั่วโมง" -> 12.68 วัน 16.33 ชั่วโมง
A41: 40 | C41: ไลน์ | D41: 45547.681 | E41: =UPPER(LEFT(F41,3))&TEXT(COUNTA($F$2:F41),"000000") -> MIL000040 | F41: Millennium Auto | G41: MGC Siam paragon | K41: จอ LED จอใหญ่ ลูกค้าเพิ่มสื่อขึ้นจอแล้ว โปรแกรมเล่นสื่อเด้งปิดโปรแกรมเอง และบางครั้งจอขึ้นสีฟ้า บางครั้งเป็นสีดำ | M41: YES | N41: รีโมท | O41: เรียบร้อยปกติ | P41: โมชิ | S41: กล่องค้าง | T41: รีสตาร์ทกล่องใช้งานได้ปกติ | U41: Panel | W41: 45548.681 | Y41: =ROUND(IF(ISBLANK(W41), (NOW() - D41) * 24 / 24, (W41 - D41) * 24 / 24), 2) & " วัน " & ROUND(MOD(IF(ISBLANK(W41), (NOW() - D41) * 24, (W41 - D41) * 24), 24), 2) & " ชั่วโมง" -> 1 วัน 0 ชั่วโมง
A42: 41 | C42: ไลน์ | D42: 45547.375 | E42: =UPPER(LEFT(F42,3))&TEXT(COUNTA($F$2:F42),"000000") -> TRU000041 | F42: TRUE | G42: True shop central ladprao | K42: สื่อที่สาขาทรูช้อบเซ็นทรัล ลาดพร้าว 80100477 ยังมีสื่อวันแม่ ขึ้นอยู่ | M42: YES | N42: รีโมท | O42: เรียบร้อยปกติ | P42: โมชิ | S42: เกิดจากการตกหล่นในการส่งขึ้นสื่อ | T42: อัพเดตสื่อขึ้นจอให้ลูกค้าใหม่ | U42: แก้ไขสื่อ | W42: 45548.681 | Y42: =ROUND(IF(ISBLANK(W42), (NOW() - D42) * 24 / 24, (W42 - D42) * 24 / 24), 2) & " วัน " & ROUND(MOD(IF(ISBLANK(W42), (NOW() - D42) * 24, (W42 - D42) * 24), 24), 2) & " ชั่วโมง" -> 1.31 วัน 7.33 ชั่วโมง
A43: 42 | C43: ไลน์ | D43: 45546.858 | E43: =UPPER(LEFT(F43,3))&TEXT(COUNTA($F$2:F43),"000000") -> BMN000042 | F43: BMN | G43: MRT Sukhumvit Cloum | K43: แจ้งซ่อมเสาสื่อ Reno12 ชั้นออกบัตรฝั่ง S แผ่นจอดับ ครับ | M43: YES | N43: รีโมท | O43: เรียบร้อยปกติ | P43: โมชิ | S43: จอไม่ติดบ้างสวน | T43: เปลี่ยนการ์ดใหม่ครับ | U43: Recive | W43: 45549.681 | Y43: =ROUND(IF(ISBLANK(W43), (NOW() - D43) * 24 / 24, (W43 - D43) * 24 / 24), 2) & " วัน " & ROUND(MOD(IF(ISBLANK(W43), (NOW() - D43) * 24, (W43 - D43) * 24), 24), 2) & " ชั่วโมง" -> 2.82 วัน 19.75 ชั่วโมง
A44: 43 | C44: ไลน์ | D44: 45554.333 | E44: =UPPER(LEFT(F44,3))&TEXT(COUNTA($F$2:F44),"000000") -> TRU000043 | F44: TRUE | G44: สำนักงานใหญ่ | K44: TV Corner : True Branding Shop Embassy, ทรู1ใยแก้ว, CP Tower, EMSPHERE, Siam soi 2 แจ้งขึ้นสื่อ iPhone 16 & 16 Pro (Launch) ระยะเวลาการขึ้นสื่อ 20 Sep เวลา 8.00 am - 30 Sep 24 ห้ามขึ้นสื่อก่อนกำหนดน | M44: YES | N44: รีโมท | O44: เรียบร้อยปกติ | P44: เหน่ง,โดม | S44: ตรวจสอบสื่อและทำการอัพ | T44: อัพสื่อเรียบร้อยครับ | U44: อัพเดทสื่อ | W44: 45554.708 | Y44: =ROUND(IF(ISBLANK(W44), (NOW() - D44) * 24 / 24, (W44 - D44) * 24 / 24), 2) & " วัน " & ROUND(MOD(IF(ISBLANK(W44), (NOW() - D44) * 24, (W44 - D44) * 24), 24), 2) & " ชั่วโมง" -> 0.38 วัน 9 ชั่วโมง | AA44: https://drive.google.com/drive/folders/1QxMYqpzFejHnMGoZiVTft4xZwnqxH5lY?usp=drive_l
A45: 44 | C45: ไลน์ | D45: 45549.681 | E45: =UPPER(LEFT(F45,3))&TEXT(COUNTA($F$2:F45),"000000") -> LAB000044 | F45: LABX | G45: 20 -ศูนย์เลเซอร์ซีคอนบางแค | K45: จอแสดงแค่ครึ่งเดียว | M45: YES | N45: แนะนำ | O45: ยกเลิก | P45: โมชิ | S45: เคสซ้ำ LA0089 | U45: Module | W45: 45549.681 | Y45: =ROUND(IF(ISBLANK(W45), (NOW() - D45) * 24 / 24, (W45 - D45) * 24 / 24), 2) & " วัน " & ROUND(MOD(IF(ISBLANK(W45), (NOW() - D45) * 24, (W45 - D45) * 24), 24), 2) & " ชั่วโมง" -> 0 วัน 0 ชั่วโมง
A46: 45 | C46: ไลน์ | D46: 243875.68 | E46: =UPPER(LEFT(F46,3))&TEXT(COUNTA($F$2:F46),"000000") -> RIC000045 | F46: Ricco | G46: Adidas CRC ชิดลม | K46: จอสีเพี้ยนขึ้นสีเขียว | M46: YES | N46: แก้ไขหน้างาน | O46: เรียบร้อยปกติ | P46: ส่าวหย่าง , ยอด , ตี๋ | Q46: 243910.88 | R46: 243911.08 | S46: ของเข้าแล้วรอ QC และจัดคิวช่างเข้า หลังห้างปิด 22:00-24:00 | T46: ดำเนินการเปลี่ยนจอเรียร้อย | U46: Panel | W46: 45585.042 | Y46: =ROUND(IF(ISBLANK(W46), (NOW() - D46) * 24 / 24, (W46 - D46) * 24 / 24), 2) & " วัน " & ROUND(MOD(IF(ISBLANK(W46), (NOW() - D46) * 24, (W46 - D46) * 24), 24), 2) & " ชั่วโมง" -> -198290.64 วัน 8.67 ชั่วโมง | AA46: ทางคุณแป้งอยากให้สั่งจอใหม่มาเปลี่ยน ภายในสัปดาห์นี้ รบกวนด้วยครับ ให้ผมเปิดPRไว้ก่อนเลยไหมครับพี่แม๊ก**รอของเข้าไทย รายละเอียดดังนี้ *จอLCD43นิ้ว 2 หน้า ที่มีปัญหา Serviceจอมาทั้งหมด 3 ครั้งแก้ไขไม่หายครับ * วันที่17/8/67 -ติดตั้งจอแล้วพาแนลแตก จอดับ 1ด้าน เข้าแก้ไขครั้งที่1 วันที่21/8/67 -เปลี่ยนพาแนลจอใหม่ ใช้งานได้ปกติ วันที่26/8/67 -ลูกค้าแจ้งว่าจอเดิมที่เปลี่ยนพาแนลการแสดงผลหน้าจอขึ้นสีเขียว เข้าแก้ไขครั้งที่2 วันที่28/8/67 -เปลี่ยนการ์ดจอใหม่ จำนวน 1 ใบ -จอใช้งานได้ปกติ วันที่12/9/67 -ลูกค้าแจ้งว่าจอเดิมที่แก้ไขล่าสุดเปลี่ยนการ์ดการแสดงผลหน้าจอขึ้นสีเขียว เข้าแก้ไขครั้งที่3 วันที่18/9/67 -เปลี่ยนพาแนลจอใหม่ (ไม่หาย) -สลับสายแพรใหม่ (ไม่หาย) -สายแพรที่นำไปเปลี่ยนสั้น ยังไม่ได้ทดสอบแก้ไข
A47: 46 | C47: ไลน์ | D47: 45548 | E47: =UPPER(LEFT(F47,3))&TEXT(COUNTA($F$2:F47),"000000") -> EVE000046 | F47: EVEANDBOY | G47: เดอะมอลล์ บางกะปิ | K47: จอสีไม่เต็ม | M47: YES | N47: แก้ไขหน้างาน | O47: เรียบร้อยปกติ | P47: "พี่เชน,บอล" | S47: แผ่นเสีย | T47: เปลี่ยนแผ่นใหม่1แผ่น | U47: Module | W47: 45553.583 | Y47: =ROUND(IF(ISBLANK(W47), (NOW() - D47) * 24 / 24, (W47 - D47) * 24 / 24), 2) & " วัน " & ROUND(MOD(IF(ISBLANK(W47), (NOW() - D47) * 24, (W47 - D47) * 24), 24), 2) & " ชั่วโมง" -> 5.58 วัน 14 ชั่วโมง | AA47: เพิ่มเติม// ลค.เเจ้งจอดับกลาง สาเหตุ/เเก้ไข้ : หม้อเเปลงเสีย// เป็นหม้อแปลงใหม่ | AB47: EV0045
A48: 47 | C48: ไลน์ | D48: 45547.5 | E48: =UPPER(LEFT(F48,3))&TEXT(COUNTA($F$2:F48),"000000") -> TRU000047 | F48: TRUE | G48: สำนักงานใหญ่ | K48: รบกวนเข้าไป Download สื่อ Focus ใหม่นะคะ ลดเหลือไฟล์เดียวรวม 2 สื่อไว้ด้วยกัน | M48: YES | N48: รีโมท | O48: ยกเลิก | P48: ไตรรัตน์ ปีกลาง_นิค | S48: เนื่องจากลิงค์สื่อที่ให้มาไม่ได้มีการเปลี่ยนแปลง | U48: อัพเดทสื่อ | W48: 45547.625 | Y48: =ROUND(IF(ISBLANK(W48), (NOW() - D48) * 24 / 24, (W48 - D48) * 24 / 24), 2) & " วัน " & ROUND(MOD(IF(ISBLANK(W48), (NOW() - D48) * 24, (W48 - D48) * 24), 24), 2) & " ชั่วโมง" -> 0.13 วัน 3 ชั่วโมง
A49: 48 | C49: ไลน์ | D49: 45548.417 | E49: =UPPER(LEFT(F49,3))&TEXT(COUNTA($F$2:F49),"000000") -> MIL000048 | F49: Millennium Auto | G49: MGC Siamparagon | I49: คุณวิ | J49: 0625938255 | K49: เข้าแก้ไขอาการจอดับ | M49: YES | N49: แก้ไขหน้างาน | O49: เรียบร้อยปกติ | P49: โมชิ | S49: มีการตั้งเวลาผิดไว้ | T49: เซ็ทเวลาเปิด-ปิดใหม่ | U49: Module | Y49: =ROUND(IF(ISBLANK(W49), (NOW() - D49) * 24 / 24, (W49 - D49) * 24 / 24), 2) & " วัน " & ROUND(MOD(IF(ISBLANK(W49), (NOW() - D49) * 24, (W49 - D49) * 24), 24), 2) & " ชั่วโมง" -> 718 วัน 0.04 ชั่วโมง
A50: 49 | C50: ไลน์ | D50: 45548.493 | E50: =UPPER(LEFT(F50,3))&TEXT(COUNTA($F$2:F50),"000000") -> BMN000049 | F50: BMN | G50: สถานีสุขุมวิท | K50: เข้าแก้ไขอาการจอดับ | M50: YES | N50: แก้ไขหน้างาน | O50: เรียบร้อยปกติ | P50: ณัฐวุฒิ อรรถประจง_โอ๋ | S50: จอดับบางส่วน | T50: 1. เปลี่ยนเบรกเกอร์กันดูด 25 แอมป์ abb 1 ตัว 2. เป็นแผ่นโมดูล 2 แผ่น แผ่นเก่าให้ยูมิยูมิน (คนจีน) | U50: Module | W50: 45555.792 | Y50: =ROUND(IF(ISBLANK(W50), (NOW() - D50) * 24 / 24, (W50 - D50) * 24 / 24), 2) & " วัน " & ROUND(MOD(IF(ISBLANK(W50), (NOW() - D50) * 24, (W50 - D50) * 24), 24), 2) & " ชั่วโมง" -> 7.3 วัน 7.17 ชั่วโมง | AB50: BM0048
A51: 50 | C51: ไลน์ | D51: 45548.5 | E51: =UPPER(LEFT(F51,3))&TEXT(COUNTA($F$2:F51),"000000") -> TRU000050 | F51: TRUE | G51: True shop central ladprao | K51: ยังขึ้นสื่อ Focus อันเก่าอยู่ | M51: YES | N51: รีโมท | O51: เรียบร้อยปกติ | P51: เหน่ง, โดม | S51: ตรวจสอบสื่อและทำการอัพ | T51: ทำการอัพสื่อเรียบร้อย | U51: อัพเดทสื่อ | W51: 45548.625 | Y51: =ROUND(IF(ISBLANK(W51), (NOW() - D51) * 24 / 24, (W51 - D51) * 24 / 24), 2) & " วัน " & ROUND(MOD(IF(ISBLANK(W51), (NOW() - D51) * 24, (W51 - D51) * 24), 24), 2) & " ชั่วโมง" -> 0.13 วัน 3 ชั่วโมง
A52: 51 | C52: ไลน์ | D52: 45548.5 | E52: =UPPER(LEFT(F52,3))&TEXT(COUNTA($F$2:F52),"000000") -> TRU000051 | F52: TRUE | G52: True shop Ayudhara Park | K52: จอ LED Wall ขึ้นผิด | M52: YES | N52: รีโมท | O52: เรียบร้อยปกติ | P52: โมชิ | S52: จอ LED Wall ขึ้นผิด | T52: ทำการอัพขึ้นใหม่ | U52: แก้ไขสื่อ | W52: 45548.625 | Y52: =ROUND(IF(ISBLANK(W52), (NOW() - D52) * 24 / 24, (W52 - D52) * 24 / 24), 2) & " วัน " & ROUND(MOD(IF(ISBLANK(W52), (NOW() - D52) * 24, (W52 - D52) * 24), 24), 2) & " ชั่วโมง" -> 0.13 วัน 3 ชั่วโมง
A53: 52 | C53: ไลน์ | D53: 45548.625 | E53: =UPPER(LEFT(F53,3))&TEXT(COUNTA($F$2:F53),"000000") -> TRU000052 | F53: TRUE | G53: true Branding Shop Embassy | K53: LED : iPhone 16 Pro Prebook (13 Sep 19.00 น. - 19 Sep 23.59 น.) | M53: YES | N53: รีโมท | O53: เรียบร้อยปกติ | P53: โมชิ | S53: ตรวจสอบสื่อและทำการอัพ | T53: ทำการอัพสื่อเรียบร้อย | U53: อัพเดทสื่อ | W53: 45549.625 | Y53: =ROUND(IF(ISBLANK(W53), (NOW() - D53) * 24 / 24, (W53 - D53) * 24 / 24), 2) & " วัน " & ROUND(MOD(IF(ISBLANK(W53), (NOW() - D53) * 24, (W53 - D53) * 24), 24), 2) & " ชั่วโมง" -> 1 วัน 0 ชั่วโมง | AA53: **ระยะเวลาการขึ้นสื่อวันนี้ Fri 13 Sep 19.00 น. - Thu 19 Sep 23.59 น. ห้ามขึ้นสื่อก่อนกำหนด
A54: 53 | C54: ไลน์ | D54: 45548.792 | E54: =UPPER(LEFT(F54,3))&TEXT(COUNTA($F$2:F54),"000000") -> TRU000053 | F54: TRUE | G54: ทรู1ใยแก้ว | K54: LED : iPhone 16 Pro Prebook (13 Sep 19.00 น. - 19 Sep 23.59 น.) | M54: YES | N54: รีโมท | O54: เรียบร้อยปกติ | P54: โมชิ | S54: ตรวจสอบสื่อและทำการอัพ | T54: ทำการอัพสื่อเรียบร้อย | U54: อัพเดทสื่อ | W54: 45549.625 | Y54: =ROUND(IF(ISBLANK(W54), (NOW() - D54) * 24 / 24, (W54 - D54) * 24 / 24), 2) & " วัน " & ROUND(MOD(IF(ISBLANK(W54), (NOW() - D54) * 24, (W54 - D54) * 24), 24), 2) & " ชั่วโมง" -> 0.83 วัน 20 ชั่วโมง | AA54: **ระยะเวลาการขึ้นสื่อวันนี้ Fri 13 Sep 19.00 น. - Thu 19 Sep 23.59 น. ห้ามขึ้นสื่อก่อนกำหนด
A55: 54 | C55: ไลน์ | D55: 45548.792 | E55: =UPPER(LEFT(F55,3))&TEXT(COUNTA($F$2:F55),"000000") -> TRU000054 | F55: TRUE | G55: CP Tower | K55: LED : iPhone 16 Pro Prebook (13 Sep 19.00 น. - 19 Sep 23.59 น.) | M55: YES | N55: รีโมท | O55: เรียบร้อยปกติ | P55: โมชิ | S55: ตรวจสอบสื่อและทำการอัพ | T55: ทำการอัพสื่อเรียบร้อย | U55: อัพเดทสื่อ | W55: 45550.625 | Y55: =ROUND(IF(ISBLANK(W55), (NOW() - D55) * 24 / 24, (W55 - D55) * 24 / 24), 2) & " วัน " & ROUND(MOD(IF(ISBLANK(W55), (NOW() - D55) * 24, (W55 - D55) * 24), 24), 2) & " ชั่วโมง" -> 1.83 วัน 20 ชั่วโมง | AA55: **ระยะเวลาการขึ้นสื่อวันนี้ Fri 13 Sep 19.00 น. - Thu 19 Sep 23.59 น. ห้ามขึ้นสื่อก่อนกำหนด
A56: 55 | C56: ไลน์ | D56: 45548.792 | E56: =UPPER(LEFT(F56,3))&TEXT(COUNTA($F$2:F56),"000000") -> TRU000055 | F56: TRUE | G56: EMSPHERE | K56: LED : iPhone 16 Pro Prebook (13 Sep 19.00 น. - 19 Sep 23.59 น.) | M56: YES | N56: รีโมท | O56: เรียบร้อยปกติ | P56: โมชิ | S56: ตรวจสอบสื่อและทำการอัพ | T56: ทำการอัพสื่อเรียบร้อย | U56: อัพเดทสื่อ | W56: 45551.625 | Y56: =ROUND(IF(ISBLANK(W56), (NOW() - D56) * 24 / 24, (W56 - D56) * 24 / 24), 2) & " วัน " & ROUND(MOD(IF(ISBLANK(W56), (NOW() - D56) * 24, (W56 - D56) * 24), 24), 2) & " ชั่วโมง" -> 2.83 วัน 20 ชั่วโมง | AA56: **ระยะเวลาการขึ้นสื่อวันนี้ Fri 13 Sep 19.00 น. - Thu 19 Sep 23.59 น. ห้ามขึ้นสื่อก่อนกำหนด
A57: 56 | C57: ไลน์ | D57: 45548.792 | E57: =UPPER(LEFT(F57,3))&TEXT(COUNTA($F$2:F57),"000000") -> TRU000056 | F57: TRUE | G57: Siam soi 2 | K57: LED : iPhone 16 Pro Prebook (13 Sep 19.00 น. - 19 Sep 23.59 น.) | M57: YES | N57: รีโมท | O57: เรียบร้อยปกติ | P57: โมชิ | S57: ตรวจสอบสื่อและทำการอัพ | T57: ทำการอัพสื่อเรียบร้อย | U57: อัพเดทสื่อ | W57: 45552.625 | Y57: =ROUND(IF(ISBLANK(W57), (NOW() - D57) * 24 / 24, (W57 - D57) * 24 / 24), 2) & " วัน " & ROUND(MOD(IF(ISBLANK(W57), (NOW() - D57) * 24, (W57 - D57) * 24), 24), 2) & " ชั่วโมง" -> 3.83 วัน 20 ชั่วโมง | AA57: **ระยะเวลาการขึ้นสื่อวันนี้ Fri 13 Sep 19.00 น. - Thu 19 Sep 23.59 น. ห้ามขึ้นสื่อก่อนกำหนด
A58: 57 | C58: ไลน์ | D58: 45548.597 | E58: =UPPER(LEFT(F58,3))&TEXT(COUNTA($F$2:F58),"000000") -> KAW000057 | F58: Kawasaki | G58: นนทบุรี | I58: แบงค์ | J58: 0820249193 | K58: จอไม่ขึ้นสื่อ มีข้อความ No Program | M58: YES | N58: แนะนำ | O58: เรียบร้อยปกติ | P58: โมชิ | S58: พบสาเหตุว่า ที่จอ ไม่มี เสารับสัญญาณไวฟาย และ เอาไว้ในจอ | T58: นำปลายสาย ออกมาไว้ด้านนอก เพื่อให้รับสัญญาณได้ดีขึ้นอีก | U58: Sending | W58: 45553.5 | Y58: =ROUND(IF(ISBLANK(W58), (NOW() - D58) * 24 / 24, (W58 - D58) * 24 / 24), 2) & " วัน " & ROUND(MOD(IF(ISBLANK(W58), (NOW() - D58) * 24, (W58 - D58) * 24), 24), 2) & " ชั่วโมง" -> 4.9 วัน 21.68 ชั่วโมง | AA58: ยังไม่มีสื่อที่จะขึ้นจอครับ เนื่องจากทางคุณนกยังไม่ได้สร้างโปรแกรม ของไทรอั้มพ์เอง และได้มี ฝากกล่องควบคุม ที่คุณนก ส่งซ่อม ฝากไว้กับ คุณแบงค์นะครับ | AB58: KA0056
A59: 58 | C59: ไลน์ | D59: 45548.625 | E59: =UPPER(LEFT(F59,3))&TEXT(COUNTA($F$2:F59),"000000") -> TRU000058 | F59: TRUE | G59: สำนักงานใหญ่ | K59: LED : iPhone 16 Pro Prebook (13 Sep 19.00 น. - 19 Sep 23.59 น.) | M59: YES | N59: รีโมท | O59: เรียบร้อยปกติ | P59: นิค | S59: ตรวจสอบสื่อและทำการอัพ | T59: ทำการอัพสื่อเรียบร้อย | U59: อัพเดทสื่อ | W59: 45548.792 | Y59: =ROUND(IF(ISBLANK(W59), (NOW() - D59) * 24 / 24, (W59 - D59) * 24 / 24), 2) & " วัน " & ROUND(MOD(IF(ISBLANK(W59), (NOW() - D59) * 24, (W59 - D59) * 24), 24), 2) & " ชั่วโมง" -> 0.17 วัน 4 ชั่วโมง
A60: 59 | C60: ไลน์ | D60: 45548.667 | E60: =UPPER(LEFT(F60,3))&TEXT(COUNTA($F$2:F60),"000000") -> SUP000059 | F60: Superdry | G60: สำนักงานใหญ่ | K60: Code ตรงโค้ดไม่โชว์เลข | M60: YES | N60: รีโมท | O60: เรียบร้อยปกติ | P60: โมชิ | S60: เครื่องค้าง | U60: Sending | W60: 45548.683 | Y60: =ROUND(IF(ISBLANK(W60), (NOW() - D60) * 24 / 24, (W60 - D60) * 24 / 24), 2) & " วัน " & ROUND(MOD(IF(ISBLANK(W60), (NOW() - D60) * 24, (W60 - D60) * 24), 24), 2) & " ชั่วโมง" -> 0.02 วัน 0.4 ชั่วโมง
A61: 60 | C61: ไลน์ | D61: 45548.667 | E61: =UPPER(LEFT(F61,3))&TEXT(COUNTA($F$2:F61),"000000") -> SUP000060 | F61: Superdry | G61: พัทยา | J61: 0645865651 | K61: จอของเทอร์มินอลพัทยาครับเชื่อมอินเตอร์เน็ตแต่มันไม่ออนไลน์ในระบบ | M61: YES | N61: รีโมท | O61: ยกเลิก | P61: โมชิ | S61: ลููกค้าแจ้งว่าใช้งานได้แล้ว | U61: Sending | Y61: =ROUND(IF(ISBLANK(W61), (NOW() - D61) * 24 / 24, (W61 - D61) * 24 / 24), 2) & " วัน " & ROUND(MOD(IF(ISBLANK(W61), (NOW() - D61) * 24, (W61 - D61) * 24), 24), 2) & " ชั่วโมง" -> 717.75 วัน 18.04 ชั่วโมง
A62: 61 | C62: ไลน์ | D62: 45548.708 | E62: =UPPER(LEFT(F62,3))&TEXT(COUNTA($F$2:F62),"000000") -> DTA000061 | F62: Dtac | G62: สำนักงานใหญ่ | K62: 1.แจ้งขึ้นสื่อ เคมเปญ เปลี่ยนจากเติมเงินเป็นรายเดือน ประจำเดือน Sep-24ระยะเวลาการขึ้นสื่อ 13 Sep 24 - 30 Sep'24 (สื่อช่องทางTrue Shop ไม่มีYoutube สื่อ Dtac มี Youtube) 2.แจ้งขึ้นสื่อ เคมเปญ iPhone 16 & 16 Pro (Pre-book) ระยะเวลาการขึ้นสื่อ 13 Sep 24 - 19 Sep'24 @Team Lead ฝากลงจอ Digital Standee | M62: YES | N62: รีโมท | O62: เรียบร้อยปกติ | P62: โมชิ | S62: ตรวจสอบสื่อและทำการอัพ | T62: ทำการอัพสื่อเรียบร้อย | U62: อัพเดทสื่อ | Y62: =ROUND(IF(ISBLANK(W62), (NOW() - D62) * 24 / 24, (W62 - D62) * 24 / 24), 2) & " วัน " & ROUND(MOD(IF(ISBLANK(W62), (NOW() - D62) * 24, (W62 - D62) * 24), 24), 2) & " ชั่วโมง" -> 717.71 วัน 17.04 ชั่วโมง | AA62: DTAC SHOP : LED,Digital Signage (จอนอก,จอใน,Digital Standee)(ฝากทีม DR ลงจอ LED Dtac แฟชั่น ไอแลน) https://drive.google.com/drive/folders/1MhBKHaPhxIUDzqUZvNImI6-BXR8xJEMQ?usp=sharing Team DR >>> Digital Screen 43" co brand (36สาขาลงสื่อเอง/Vendeลงให้)ฝากทีม DR https://drive.google.com/drive/folders/1MhBKHaPhxIUDzqUZvNImI6-BXR8xJEMQ?usp=sharing
A63: 62 | C63: ไลน์ | D63: 45503 | E63: =UPPER(LEFT(F63,3))&TEXT(COUNTA($F$2:F63),"000000") -> BMN000062 | F63: BMN | G63: MRT จัตุจักร | K63: แผ่นโมดูลหลุด 1 จุด | M63: YES | N63: แก้ไขหน้างาน | O63: เรียบร้อยปกติ | P63: โมชิ | S63: น่าจะโดนกระเป๋าลูกค้าเกี่ยวโดนแผ่นทำให้แผ่นเราหลุด | T63: ติดตั้งแผ่นกลับคืนที่เดิมหน้าจอใช้งานได้ปกติ | U63: Module | W63: 45503.667 | Y63: =ROUND(IF(ISBLANK(W63), (NOW() - D63) * 24 / 24, (W63 - D63) * 24 / 24), 2) & " วัน " & ROUND(MOD(IF(ISBLANK(W63), (NOW() - D63) * 24, (W63 - D63) * 24), 24), 2) & " ชั่วโมง" -> 0.67 วัน 16 ชั่วโมง
A64: 63 | C64: ไลน์ | D64: 45504 | E64: =UPPER(LEFT(F64,3))&TEXT(COUNTA($F$2:F64),"000000") -> BMN000063 | F64: BMN | G64: MRT สุขุมวิท | K64: จอ LED ดับไม่เล่นสื่อ | M64: YES | N64: แก้ไขหน้างาน | O64: เรียบร้อยปกติ | S64: เข้าตรวจสอบ จอ LED และระบบไฟ ทำงานปกติ พบว่า player ไม่ทำงาน แจ้งทีม player เข้าตรวจสอบ | U64: Module | W64: 45504.466 | Y64: =ROUND(IF(ISBLANK(W64), (NOW() - D64) * 24 / 24, (W64 - D64) * 24 / 24), 2) & " วัน " & ROUND(MOD(IF(ISBLANK(W64), (NOW() - D64) * 24, (W64 - D64) * 24), 24), 2) & " ชั่วโมง" -> 0.47 วัน 11.18 ชั่วโมง
A65: 64 | C65: ไลน์ | D65: 45505 | E65: =UPPER(LEFT(F65,3))&TEXT(COUNTA($F$2:F65),"000000") -> BMN000064 | F65: BMN | G65: MRT เพชรบุุรี | K65: แผ่นโมดูลดัับ | M65: YES | N65: แก้ไขหน้างาน | O65: เรียบร้อยปกติ | S65: ผลการตรวจสอบ // -เสาเลขที่ 07B แผ่นโมดูลมีอาการดับบางส่วน - เสาเลขที่ 09B สายแพรหลุด | T65: เสาเลขที่ 07B เปลี่ยนแผ่นโมดูลจำนวน1แผ่น เสาเลขที่ 09B สายแพรหลุด ได้ทำการแก้ไขด้วย การเปลี่ยนสายแพรจำนวน 1 เส้น สถานะจอ //ปกติทั้ง 07/09B | U65: Module | W65: 45505.917 | Y65: =ROUND(IF(ISBLANK(W65), (NOW() - D65) * 24 / 24, (W65 - D65) * 24 / 24), 2) & " วัน " & ROUND(MOD(IF(ISBLANK(W65), (NOW() - D65) * 24, (W65 - D65) * 24), 24), 2) & " ชั่วโมง" -> 0.92 วัน 22 ชั่วโมง
A66: 65 | C66: ไลน์ | D66: 45505 | E66: =UPPER(LEFT(F66,3))&TEXT(COUNTA($F$2:F66),"000000") -> BMN000065 | F66: BMN | G66: MRT สุขุมวิท | K66: จอดับไม่เล่นสื่อ | M66: YES | N66: แก้ไขหน้างาน | O66: เรียบร้อยปกติ | S66: ผลการตรวจสอบ : ทีมเข้าตรวจสอ ถึงหน้างานจอติดปกติ จอ LED และระบบไฟ ทำงานปกติ สาเหตุเกิดจากการตั้งเวลาเล่นสื่อของระบบหลังบ้านค่ะ | T66: ส่งโปรแกรมสื่อขึ้นจอให้ใหม่ ในวันที่ 1/8/67 หน้าจอใช้งานได้ปกติ | U66: Module | W66: 45505.462 | Y66: =ROUND(IF(ISBLANK(W66), (NOW() - D66) * 24 / 24, (W66 - D66) * 24 / 24), 2) & " วัน " & ROUND(MOD(IF(ISBLANK(W66), (NOW() - D66) * 24, (W66 - D66) * 24), 24), 2) & " ชั่วโมง" -> 0.46 วัน 11.08 ชั่วโมง
A67: 66 | C67: ไลน์ | D67: 45510 | E67: =UPPER(LEFT(F67,3))&TEXT(COUNTA($F$2:F67),"000000") -> BMN000066 | F67: BMN | G67: MRT สุขุมวิท | K67: สื่อเล่นเพี้ยน | M67: YES | N67: แก้ไขหน้างาน | O67: เรียบร้อยปกติ | S67: ผลการตรวจสอบ : หัวสายแลนมีปัญหา | T67: ยั้มหัวสายแลนใหม่ทั้ง2ฝั่ง ฝั่งคอนโทรลและฝั่งจอ จอใช้งานได้ปกติ | U67: Module | W67: 45510.569 | Y67: =ROUND(IF(ISBLANK(W67), (NOW() - D67) * 24 / 24, (W67 - D67) * 24 / 24), 2) & " วัน " & ROUND(MOD(IF(ISBLANK(W67), (NOW() - D67) * 24, (W67 - D67) * 24), 24), 2) & " ชั่วโมง" -> 0.57 วัน 13.65 ชั่วโมง
A68: 67 | C68: ไลน์ | D68: 45515 | E68: =UPPER(LEFT(F68,3))&TEXT(COUNTA($F$2:F68),"000000") -> BMN000067 | F68: BMN | G68: MRT สุขุมวิท | K68: จอไม่ขึ้นภาพทั้ง 3 จอ | M68: YES | N68: แก้ไขหน้างาน | O68: เรียบร้อยปกติ | S68: ผลการตรวตสอบ : เบรกเกอร์หลักทิป ไม่จ่ายไฟมายังอุปกรณ์ | T68: ออนเบรกเกอร์, ตั้งไทม์เมอร์ใหม่ จอสามารถใช้งานได้ปกติ | U68: Module | W68: 45515.792 | Y68: =ROUND(IF(ISBLANK(W68), (NOW() - D68) * 24 / 24, (W68 - D68) * 24 / 24), 2) & " วัน " & ROUND(MOD(IF(ISBLANK(W68), (NOW() - D68) * 24, (W68 - D68) * 24), 24), 2) & " ชั่วโมง" -> 0.79 วัน 19 ชั่วโมง
A69: 68 | C69: ไลน์ | D69: 45519 | E69: =UPPER(LEFT(F69,3))&TEXT(COUNTA($F$2:F69),"000000") -> BMN000068 | F69: BMN | G69: MRT ศูนย์การประชุมฯ | K69: จอ LED ดับบางส่วน | M69: YES | N69: แก้ไขหน้างาน | O69: เรียบร้อยปกติ | S69: หม้อแปลงเสีย 1 ใบ | T69: เปลี่ยนหม้อแปลง 1 ใบ จอใช้งานได้ปกติ | U69: Module | W69: 45519.562 | Y69: =ROUND(IF(ISBLANK(W69), (NOW() - D69) * 24 / 24, (W69 - D69) * 24 / 24), 2) & " วัน " & ROUND(MOD(IF(ISBLANK(W69), (NOW() - D69) * 24, (W69 - D69) * 24), 24), 2) & " ชั่วโมง" -> 0.56 วัน 13.5 ชั่วโมง
A70: 69 | C70: ไลน์ | D70: 45520 | E70: =UPPER(LEFT(F70,3))&TEXT(COUNTA($F$2:F70),"000000") -> BMN000069 | F70: BMN | G70: MRT จัตุุจักร | K70: จอ LED ดับบางส่วน | M70: YES | N70: แก้ไขหน้างาน | O70: เรียบร้อยปกติ | S70: แผ่นโมดูลเสีย 1 แผ่น | T70: เปลี่ยนแผ่นโมดูลเสีย จำนวน 1 แผ่น จอใช้งานได้ปกติ | U70: Module | W70: 45520.46 | Y70: =ROUND(IF(ISBLANK(W70), (NOW() - D70) * 24 / 24, (W70 - D70) * 24 / 24), 2) & " วัน " & ROUND(MOD(IF(ISBLANK(W70), (NOW() - D70) * 24, (W70 - D70) * 24), 24), 2) & " ชั่วโมง" -> 0.46 วัน 11.03 ชั่วโมง
A71: 70 | C71: ไลน์ | D71: 45526 | E71: =UPPER(LEFT(F71,3))&TEXT(COUNTA($F$2:F71),"000000") -> BMN000070 | F71: BMN | G71: MRT จัตุจักร | K71: แนวแผ่นไม่เสมอ | M71: YES | N71: แก้ไขหน้างาน | O71: เรียบร้อยปกติ | S71: เกิดจากการได้รับแรงกระแทก | T71: เข้าปรับแผ่นเสาเลื่อน จอสามารถใช้งานได้ปกติ | U71: Module | W71: 45526.844 | Y71: =ROUND(IF(ISBLANK(W71), (NOW() - D71) * 24 / 24, (W71 - D71) * 24 / 24), 2) & " วัน " & ROUND(MOD(IF(ISBLANK(W71), (NOW() - D71) * 24, (W71 - D71) * 24), 24), 2) & " ชั่วโมง" -> 0.84 วัน 20.27 ชั่วโมง
A72: 71 | C72: ไลน์ | D72: 45532 | E72: =UPPER(LEFT(F72,3))&TEXT(COUNTA($F$2:F72),"000000") -> BMN000071 | F72: BMN | G72: MRT สุขุมวิท | K72: แผ่นโมดูลสีีเพี้ยน | M72: YES | N72: แก้ไขหน้างาน | O72: เรียบร้อยปกติ | S72: สายแพรจอเสีย | T72: เปลี่ยนสายแพร 1 เส้น จอใช้งานได้ปกติ | U72: Module | W72: 45532.042 | Y72: =ROUND(IF(ISBLANK(W72), (NOW() - D72) * 24 / 24, (W72 - D72) * 24 / 24), 2) & " วัน " & ROUND(MOD(IF(ISBLANK(W72), (NOW() - D72) * 24, (W72 - D72) * 24), 24), 2) & " ชั่วโมง" -> 0.04 วัน 1 ชั่วโมง
A73: 72 | C73: ไลน์ | D73: 45539 | E73: =UPPER(LEFT(F73,3))&TEXT(COUNTA($F$2:F73),"000000") -> BMN000072 | F73: BMN | G73: MRT จัตุจักร | K73: แนวแผ่นไม่เสมอ | M73: YES | N73: แก้ไขหน้างาน | O73: เรียบร้อยปกติ | S73: เกิดจากการได้รับแรงกระแทก | T73: ปรับรอยต่อแผ่น เช็คจำนวนแผ่นเสีย จอใช้งานได้ปกติ | U73: Module | W73: 45539.819 | Y73: =ROUND(IF(ISBLANK(W73), (NOW() - D73) * 24 / 24, (W73 - D73) * 24 / 24), 2) & " วัน " & ROUND(MOD(IF(ISBLANK(W73), (NOW() - D73) * 24, (W73 - D73) * 24), 24), 2) & " ชั่วโมง" -> 0.82 วัน 19.67 ชั่วโมง
A74: 73 | C74: ไลน์ | D74: 45546 | E74: =UPPER(LEFT(F74,3))&TEXT(COUNTA($F$2:F74),"000000") -> BMN000073 | F74: BMN | G74: MRT สุขุมวิท | K74: จอไม่ติดบางส่วน | M74: YES | N74: แก้ไขหน้างาน | O74: เรียบร้อยปกติ | S74: Receiving Card เสีย 1 ใบ | T74: เปลี่ยน Receiving Card ใหม่ จอสามารถใช้งานได้ปกติ | U74: Module | W74: 45546.858 | Y74: =ROUND(IF(ISBLANK(W74), (NOW() - D74) * 24 / 24, (W74 - D74) * 24 / 24), 2) & " วัน " & ROUND(MOD(IF(ISBLANK(W74), (NOW() - D74) * 24, (W74 - D74) * 24), 24), 2) & " ชั่วโมง" -> 0.86 วัน 20.58 ชั่วโมง
A75: 74 | C75: ไลน์ | D75: 45548 | E75: =UPPER(LEFT(F75,3))&TEXT(COUNTA($F$2:F75),"000000") -> DTA000074 | F75: Dtac | G75: สำนักงานใหญ่ | K75: "เพิ่มสื่อ iPhone 16 Pro Prebook เริ่มขึ้นสื่อ 13 Sep 2024 ตั้งแต่ 19.00 น. สื่อแต่ละช็อปจะทะยอยเพิ่มเข้าไปใน Link A. Highlight Campaign ไม่มีสื่อ ------------------------------------- B. Commercial Campaign -True Coffee (TS Mega Bangna) -True ID Promote Thai League (ตามลิสสาขาที่มี) (13 Aug 2024-31 May 2025) -TVS NOW-EPL Sep2024 (New!!!) -TVS-EPL Sep2024 -True Online -True5G Postpaid (1/9/2024-31/10/2024)(ตามลิสสาขาที่มี) -iPhone 16 Pro Prebook (13 Sep 19.00 น. - 19 Sep 23.59 น.) (ตามลิสสาขาที่มี) (New!!!) -Huawei Matepad SE11 (ตามลิสสาขาที่มี) -Realme 12X exclusive TRUE DTAC -VIVO V40 (New!!!) -Samsung Flip 6 Fold 6 -OPPO Reno 12" | M75: YES | N75: รีโมท | O75: เรียบร้อยปกติ | S75: ตรวจสอบสื่อและทำการอัพ | T75: อัพสื่อเรียบร้อยครับ | U75: อัพเดทสื่อ | W75: 45549.354 | Y75: =ROUND(IF(ISBLANK(W75), (NOW() - D75) * 24 / 24, (W75 - D75) * 24 / 24), 2) & " วัน " & ROUND(MOD(IF(ISBLANK(W75), (NOW() - D75) * 24, (W75 - D75) * 24), 24), 2) & " ชั่วโมง" -> 1.35 วัน 8.5 ชั่วโมง
A76: 75 | C76: ไลน์ | D76: 45548 | E76: =UPPER(LEFT(F76,3))&TEXT(COUNTA($F$2:F76),"000000") -> BMN000075 | F76: BMN | G76: MRT สุขุมวิท | K76: แจ้งซ่อมจอ สื่อ LED ฝั่งทางเชื่อม BTS ระหว่างทาง เดิน ประตู 1กับประตู 2 ดับ 1ส่วน | M76: YES | N76: แก้ไขหน้างาน | O76: เรียบร้อยปกติ | P76: โมชิ | S76: จอled ดับบ้างส่วน | T76: เบรกเกอร์จอตัวที่ 3 ยังไม่เปิดหรือทริป เปิดกลับไปใหม่ | U76: Module | W76: 45548 | Y76: =ROUND(IF(ISBLANK(W76), (NOW() - D76) * 24 / 24, (W76 - D76) * 24 / 24), 2) & " วัน " & ROUND(MOD(IF(ISBLANK(W76), (NOW() - D76) * 24, (W76 - D76) * 24), 24), 2) & " ชั่วโมง" -> 0 วัน 0 ชั่วโมง
A77: 76 | C77: ไลน์ | D77: 45554.333 | E77: =UPPER(LEFT(F77,3))&TEXT(COUNTA($F$2:F77),"000000") -> TRU000076 | F77: TRUE | G77: สำนักงานใหญ่ | K77: เนื่องจากสาขาเปิดให้บริการส่งมอบ iPhone ร้านเปิด 8.00 น. วันที่ 20 Sep 2024 (วันเดียว) จำนวน 10 สาขา 1. True Branding Soi2 2. True Branding Soi3. 3. True Branding Shop Lotus North 4. True Branding Shop CP Tower 5. True Branding Shop True Tower1 6. True Branding Shop EmSphere 7. TrueSphere & Branding Iconsiam 8.TrueSphere EmQuartier 9.TrueSphere Huahin 10.TrueSphere Future Park Rungsit | M77: YES | N77: รีโมท | O77: เรียบร้อยปกติ | P77: เหน่ง, โดม | S77: ตรวจสอบสื่อและทำการอัพ | T77: อัพสื่อเรียบร้อยครับ | U77: อัพเดทสื่อ | W77: 45554.708 | Y77: =ROUND(IF(ISBLANK(W77), (NOW() - D77) * 24 / 24, (W77 - D77) * 24 / 24), 2) & " วัน " & ROUND(MOD(IF(ISBLANK(W77), (NOW() - D77) * 24, (W77 - D77) * 24), 24), 2) & " ชั่วโมง" -> 0.38 วัน 9 ชั่วโมง
A78: 77 | C78: ไลน์ | D78: 45549.466 | E78: =UPPER(LEFT(F78,3))&TEXT(COUNTA($F$2:F78),"000000") -> RIC000077 | F78: Ricco | G78: Adidas แฟชั่นไอส์แลนด์ | I78: คุณกุ้ง | J78: 0826249547 | K78: จอสปอร์ตเวิลด์ รูปเอียง | M78: YES | N78: แก้ไขหน้างาน | O78: เรียบร้อยปกติ | P78: โมชิ | S78: จอทีวีไม่ติดเข้าตรวจสอบอาการจอดับ เข้าเช็คจอถูกปิดอยู่ เปิดจอแล้วขึ้น SOURCE HDMI 2 เช็คสายHDMIเสียบอยู่ SOURCE HDMI 3 | T78: ปรับมาSOURCE 3 จอติดเรียบร้อย | U78: Module | W78: 45554.613 | Y78: =ROUND(IF(ISBLANK(W78), (NOW() - D78) * 24 / 24, (W78 - D78) * 24 / 24), 2) & " วัน " & ROUND(MOD(IF(ISBLANK(W78), (NOW() - D78) * 24, (W78 - D78) * 24), 24), 2) & " ชั่วโมง" -> 5.15 วัน 3.53 ชั่วโมง | AB78: AD0076
A79: 78 | C79: ไลน์ | D79: 243875.6 | E79: =UPPER(LEFT(F79,3))&TEXT(COUNTA($F$2:F79),"000000") -> WOR000078 | F79: Worko | G79: Adidas สยามสแควร์วัน SQ1 | K79: จอแจ้งซ่อม ฟาสาท D1 | M79: NO | N79: แก้ไขหน้างาน | O79: เรียบร้อยปกติ | P79: ส่าวหย่าง | Q79: 45587.917 | R79: 45588.042 | S79: ค่าช่างเทคส่าวหยาง 1 คน ลูกมือ1 คนซ่อมแผ่นจอ C2 หน้างาน จำนวน 2แผ่น มีเคสพ่วง WOR000142 | T79: ดำเนินการซ่อมเรียบร้อย | U79: Module | W79: 45587.979 | Y79: =ROUND(IF(ISBLANK(W79), (NOW() - D79) * 24 / 24, (W79 - D79) * 24 / 24), 2) & " วัน " & ROUND(MOD(IF(ISBLANK(W79), (NOW() - D79) * 24, (W79 - D79) * 24), 24), 2) & " ชั่วโมง" -> -198287.62 วัน 9.13 ชั่วโมง | AA79: มีเคสพ่วง WOR000142
A80: 79 | B80: 7343318 | C80: ไลน์ | D80: 45549.642 | E80: =UPPER(LEFT(F80,3))&TEXT(COUNTA($F$2:F80),"000000") -> TRU000079 | F80: TRUE | G80: True Shop Central Plaza Ramindra | I80: ปรัชญา/วีรญา | J80: 0825288246/0959599935 | K80: LED Wall จอดับ | M80: YES | N80: รีโมท | O80: เรียบร้อยปกติ | P80: ศรันย์ | S80: ตัว Box Player ค้าง | T80: รีสตาทในระบบ | U80: Module | W80: 45549.66 | Y80: =ROUND(IF(ISBLANK(W80), (NOW() - D80) * 24 / 24, (W80 - D80) * 24 / 24), 2) & " วัน " & ROUND(MOD(IF(ISBLANK(W80), (NOW() - D80) * 24, (W80 - D80) * 24), 24), 2) & " ชั่วโมง" -> 0.02 วัน 0.42 ชั่วโมง | AB80: TR0078
A81: 80 | C81: ไลน์ | D81: 45551.333 | E81: =UPPER(LEFT(F81,3))&TEXT(COUNTA($F$2:F81),"000000") -> TRU000080 | F81: TRUE | G81: สำนักงานใหญ่ | K81: 1.แจ้งขึ้นสื่อ เคมเปญ IPone 16 ซื้อปีนี้แลกรุ่นใหม่ปีหน้า ประจำเดือน Sep-24ระยะเวลาการขึ้นสื่อ 13 Sep 24 - 30 Sep'24 | M81: YES | N81: รีโมท | O81: เรียบร้อยปกติ | P81: โมชิ | S81: อัพเดตสื่อเรียบร้อยครับ | U81: อัพเดทสื่อ | Y81: =ROUND(IF(ISBLANK(W81), (NOW() - D81) * 24 / 24, (W81 - D81) * 24 / 24), 2) & " วัน " & ROUND(MOD(IF(ISBLANK(W81), (NOW() - D81) * 24, (W81 - D81) * 24), 24), 2) & " ชั่วโมง" -> 715.08 วัน 2.04 ชั่วโมง
A82: 81 | B82: 7344814 | C82: ไลน์ | D82: 45551.401 | E82: =UPPER(LEFT(F82,3))&TEXT(COUNTA($F$2:F82),"000000") -> TRU000081 | F82: TRUE | G82: True Shop Central Ladprao | K82: LED Wall จอโค้ง จอเป็นเส้น จอกระพริบ ตามภาพแนบ | M82: YES | N82: แก้ไขหน้างาน | O82: เรียบร้อยปกติ | P82: โมชิ | S82: 1.ตรวจเช็คกระแสไฟ มีกระแสไฟวิ่งอยู่ ที่ 27 AC 2.ตรวจสอบหม้อแปลง แล้วพบว่า น๊อตขัน L รูด | T82: 1.เปลี่ยนหม้อแปลง และเช็คไฟ วัดค่าได้ 32 AC | U82: Module | W82: 45552.833 | Y82: =ROUND(IF(ISBLANK(W82), (NOW() - D82) * 24 / 24, (W82 - D82) * 24 / 24), 2) & " วัน " & ROUND(MOD(IF(ISBLANK(W82), (NOW() - D82) * 24, (W82 - D82) * 24), 24), 2) & " ชั่วโมง" -> 1.43 วัน 10.38 ชั่วโมง | AA82: (ได้มีการเฝ้าดูอาการก่อนส่งมอบงานกับทาง ผจก เป็นเวลา 20 นาที ครับ ) | AB82: TR0080
A83: 82 | C83: ไลน์ | D83: 45551.444 | E83: =UPPER(LEFT(F83,3))&TEXT(COUNTA($F$2:F83),"000000") -> EVE000082 | F83: EVEANDBOY | G83: 12_ASK | K83: เพลงไม่ดัง | M83: YES | N83: แนะนำ | O83: เรียบร้อยปกติ | P83: หมี, นิค | S83: ทำการประสานให้หน้าร้านทดสอบเสียงโดยการใช้หูฟังทดสอบพบว่ามีเสียงมา | T83: ประสานให้หน้าร้านให้แจ้งเข้าสำนักงาน เนื่องจากอุปกรณ์ ลำโพง,สายเชื่อมต่อ เป็นของ ซัพอีกเจ้า | U83: Sending | W83: 45551.618 | Y83: =ROUND(IF(ISBLANK(W83), (NOW() - D83) * 24 / 24, (W83 - D83) * 24 / 24), 2) & " วัน " & ROUND(MOD(IF(ISBLANK(W83), (NOW() - D83) * 24, (W83 - D83) * 24), 24), 2) & " ชั่วโมง" -> 0.17 วัน 4.17 ชั่วโมง
A84: 83 | C84: ไลน์ | D84: 45551.465 | E84: =UPPER(LEFT(F84,3))&TEXT(COUNTA($F$2:F84),"000000") -> TRU000083 | F84: TRUE | G84: สำนักงานใหญ่ | K84: แจ้งขึ้นสื่อ TVC iPhone 16 & Accessories มีผล 14-30 Sep 24 | M84: YES | N84: รีโมท | O84: เรียบร้อยปกติ | P84: โมชิ | S84: อัพเดตสื่อเรียบร้อยครับ | U84: อัพเดทสื่อ | W84: 45552.479 | Y84: =ROUND(IF(ISBLANK(W84), (NOW() - D84) * 24 / 24, (W84 - D84) * 24 / 24), 2) & " วัน " & ROUND(MOD(IF(ISBLANK(W84), (NOW() - D84) * 24, (W84 - D84) * 24), 24), 2) & " ชั่วโมง" -> 1.01 วัน 0.35 ชั่วโมง
A85: 84 | C85: ไลน์ | D85: 45551.556 | E85: =UPPER(LEFT(F85,3))&TEXT(COUNTA($F$2:F85),"000000") -> BMN000084 | F85: BMN | G85: ทางด่วน ด่านสุขุมวิท | K85: ดับ 2 จอ | M85: YES | N85: แก้ไขหน้างาน | O85: เรียบร้อยปกติ | P85: โมชิ | S85: หัวRJ เมน lan จอ2 เสีย ทำให้ไม่ส่งสัญญาณไปจอที่เหลือ | T85: เปลี่ยนหัว RJ ให้ใหม่ | U85: Module | W85: 45552.352 | Y85: =ROUND(IF(ISBLANK(W85), (NOW() - D85) * 24 / 24, (W85 - D85) * 24 / 24), 2) & " วัน " & ROUND(MOD(IF(ISBLANK(W85), (NOW() - D85) * 24, (W85 - D85) * 24), 24), 2) & " ชั่วโมง" -> 0.8 วัน 19.1 ชั่วโมง | AA85: สายเมน LAN เข้าจอไม่ใช่ของ DR เดินมา | AB85: BM0083
A86: 85 | C86: ไลน์ | D86: 45551.59 | E86: =UPPER(LEFT(F86,3))&TEXT(COUNTA($F$2:F86),"000000") -> VES000085 | F86: Vespa | G86: สระบุรี | I86: คุณเอิร์ท | J86: 0898018652 | K86: จอ Digital Kiosk ของเวสป้าสระบุรี เปิดไม่ติดครับ | M86: YES | N86: แก้ไขหน้างาน | O86: เรียบร้อยปกติ | P86: ส่าวหย่าง | S86: Adapter เสีย | T86: สาขาเปลี่ยน Adaptor ใหม่ | U86: Adaptor | W86: 45562.701 | Y86: =ROUND(IF(ISBLANK(W86), (NOW() - D86) * 24 / 24, (W86 - D86) * 24 / 24), 2) & " วัน " & ROUND(MOD(IF(ISBLANK(W86), (NOW() - D86) * 24, (W86 - D86) * 24), 24), 2) & " ชั่วโมง" -> 11.11 วัน 2.68 ชั่วโมง | AA86: 1. ค่า adaptor Player Box จำนวน 1 อัน 2. ค่าบริการในการจัดส่ง | AB86: VE0084
A87: 86 | C87: ไลน์ | D87: 45551.613 | E87: =UPPER(LEFT(F87,3))&TEXT(COUNTA($F$2:F87),"000000") -> LAG000086 | F87: Laguna Property | G87: ภูเก็ต | I87: คุณแอ้ | J87: 0875778994 | K87: จอไม่ขึ้นภาพ | M87: YES | N87: แก้ไขหน้างาน | O87: เรียบร้อยปกติ | P87: ปุ้ย | S87: แผ่นเสีย 7แผ่น | T87: /เปลี่ยนแผ่นทั้งหมด 7 แผ่น จอwall 5 แผ่น จอแสตน 2 แผ่น | U87: Module | W87: 45568.604 | Y87: =ROUND(IF(ISBLANK(W87), (NOW() - D87) * 24 / 24, (W87 - D87) * 24 / 24), 2) & " วัน " & ROUND(MOD(IF(ISBLANK(W87), (NOW() - D87) * 24, (W87 - D87) * 24), 24), 2) & " ชั่วโมง" -> 16.99 วัน 23.8 ชั่วโมง | AA87: chawisa.e@groupbanyan.com
A88: 87 | C88: ไลน์ | D88: 45550.666 | E88: =UPPER(LEFT(F88,3))&TEXT(COUNTA($F$2:F88),"000000") -> TRU000087 | F88: TRUE | G88: สำนักงานใหญ่ | K88: A. Highlight Campaign -Co Brand (ตามลิสสาขาที่มี) (New!!!) ------------------------------------- B. Commercial Campaign -True Coffee (TS Mega Bangna) -True ID Promote Thai League (ตามลิสสาขาที่มี) (13 Aug 2024-31 May 2025) -TVS NOW-EPL Sep2024 -TVS-EPL Sep2024 -True Online -True5G Postpaid (1/9/2024-31/10/2024)(ตามลิสสาขาที่มี) -Huawei Matepad SE11 (ตามลิสสาขาที่มี) -Realme 12X exclusive TRUE DTAC -VIVO V40 (New!!!) -Samsung Flip 6 Fold 6 -OPPO Reno 12 | M88: YES | N88: รีโมท | O88: เรียบร้อยปกติ | P88: เหน่ง, แรมโบ้ | Q88: 45568.542 | S88: อัพเดตสื่อเรียบร้อยครับ | U88: อัพเดทสื่อ | W88: 45552.479 | Y88: =ROUND(IF(ISBLANK(W88), (NOW() - D88) * 24 / 24, (W88 - D88) * 24 / 24), 2) & " วัน " & ROUND(MOD(IF(ISBLANK(W88), (NOW() - D88) * 24, (W88 - D88) * 24), 24), 2) & " ชั่วโมง" -> 1.81 วัน 19.52 ชั่วโมง | AA88: https://drive.google.com/drive/folders/1-Y54P7v6j8Fs4Ngryn_l9uXTNk5Sm4Ma?usp=share_link
A89: 88 | C89: ไลน์ | D89: 45551.676 | E89: =UPPER(LEFT(F89,3))&TEXT(COUNTA($F$2:F89),"000000") -> TRU000088 | F89: TRUE | G89: สำนักงานใหญ่ | K89: ร้านไหนไม่มีจอกลาง ขึ้นสื่อ Logo แทนไปก่อน True Logo สำหรับจอ LED3,4 ที่เป็นจอกลาง สำหรับใช้ขึ้นในกรณีที่สื่อบางตัวไม่ทำจอ 3,4 มาให้ | M89: YES | N89: รีโมท | O89: เรียบร้อยปกติ | P89: โมชิ | S89: อัพเดตสื่อเรียบร้อยครับ | U89: อัพเดทสื่อ | W89: 45552.479 | Y89: =ROUND(IF(ISBLANK(W89), (NOW() - D89) * 24 / 24, (W89 - D89) * 24 / 24), 2) & " วัน " & ROUND(MOD(IF(ISBLANK(W89), (NOW() - D89) * 24, (W89 - D89) * 24), 24), 2) & " ชั่วโมง" -> 0.8 วัน 19.28 ชั่วโมง | AA89: https://drive.google.com/drive/folders/1M58FcPsVoE2MBhB41rXqJKhcjriktHC_?usp=sharing
A90: 89 | C90: ไลน์ | D90: 45551.688 | E90: =UPPER(LEFT(F90,3))&TEXT(COUNTA($F$2:F90),"000000") -> TRU000089 | F90: TRUE | G90: สำนักงานใหญ่ | K90: 1.แจ้งขึ้นสื่อ Trade-in Flow iPhone ระยะเวลาการขึ้นสื่อ 16 Sep 24 - 30 Oct'24 2.แจ้งขึ้นสื่อ เคมเปญ Business One Call ระยะเวลาการขึ้นสื่อ 16 Sep 24 - 31 Oct'24 3.แจ้งขึ้นสื่อ เคมเปญ Accessories Iphone16 ระยะเวลาการขึ้นสื่อ 16 Sep 24 - 31 Oct'24 | M90: YES | N90: รีโมท | O90: เรียบร้อยปกติ | P90: โมชิ | S90: อัพเดตสื่อเรียบร้อยครับ | U90: อัพเดทสื่อ | Y90: =ROUND(IF(ISBLANK(W90), (NOW() - D90) * 24 / 24, (W90 - D90) * 24 / 24), 2) & " วัน " & ROUND(MOD(IF(ISBLANK(W90), (NOW() - D90) * 24, (W90 - D90) * 24), 24), 2) & " ชั่วโมง" -> 714.73 วัน 17.52 ชั่วโมง | AA90: DTAC SHOP : LED,Digital Signage (จอนอก,จอใน,Digital Standee)(ฝากทีม DR ลงจอ LED Dtac แฟชั่น ไอแลน) https://drive.google.com/drive/folders/1INbB7b5h4ipjwcHP5yxpt4YuQUW4ZuEr?usp=sharing Team DR >>> Digital Screen 43" co brand (36สาขาลงสื่อเอง/Vendeลงให้)ฝากทีม DR https://drive.google.com/drive/folders/1INbB7b5h4ipjwcHP5yxpt4YuQUW4ZuEr?usp=sharing
A91: 90 | C91: ไลน์ | D91: 45552.348 | E91: =UPPER(LEFT(F91,3))&TEXT(COUNTA($F$2:F91),"000000") -> LAB000090 | F91: LABX | G91: ซีคอน บางแค | K91: จอภาพติดบ้างไม่ติดบ้าง | M91: YES | N91: แนะนำ | O91: เรียบร้อยปกติ | P91: โมชิ | S91: สาเหตุที่ทำให้จอดับเกิดจากช่องเสียบสายแลนเสีย | T91: ทีมเปลี่ยนการ์ดใหม่ 1 ใบ | U91: Module | W91: 45553.531 | Y91: =ROUND(IF(ISBLANK(W91), (NOW() - D91) * 24 / 24, (W91 - D91) * 24 / 24), 2) & " วัน " & ROUND(MOD(IF(ISBLANK(W91), (NOW() - D91) * 24, (W91 - D91) * 24), 24), 2) & " ชั่วโมง" -> 1.18 วัน 4.4 ชั่วโมง | AB91: LA0089
A92: 91 | C92: ไลน์ | D92: 45552.348 | E92: =UPPER(LEFT(F92,3))&TEXT(COUNTA($F$2:F92),"000000") -> TKC000091 | F92: TKC | G92: ทองหล่อ | K92: ไม่ดับตามเวลาที่กำหนด | M92: YES | N92: แนะนำ | O92: เรียบร้อยปกติ | P92: ฟลุ๊ค | S92: ตัว Timer ทำงานตามที่กำหนด | T92: ประสานงานแจ้งทางคุณส้ม Iso ให้ดำเนินการเข้าแก้ไข | U92: Timer | W92: 45552.417 | Y92: =ROUND(IF(ISBLANK(W92), (NOW() - D92) * 24 / 24, (W92 - D92) * 24 / 24), 2) & " วัน " & ROUND(MOD(IF(ISBLANK(W92), (NOW() - D92) * 24, (W92 - D92) * 24), 24), 2) & " ชั่วโมง" -> 0.07 วัน 1.65 ชั่วโมง | AA92: เนื่องจากตัวทามเมอร์เป็นของทางทีม Iso
A93: 92 | C93: ไลน์ | D93: 45552.451 | E93: =UPPER(LEFT(F93,3))&TEXT(COUNTA($F$2:F93),"000000") -> TRU000092 | F93: TRUE | G93: True shop Ayudhara Park | K93: สื่อผิด | M93: YES | N93: รีโมท | O93: ยกเลิก | P93: หนูเล็ก | S93: เปิดงานซ้ำ | T93: TR0050 | U93: แก้ไขสื่อ | W93: 45552.458 | Y93: =ROUND(IF(ISBLANK(W93), (NOW() - D93) * 24 / 24, (W93 - D93) * 24 / 24), 2) & " วัน " & ROUND(MOD(IF(ISBLANK(W93), (NOW() - D93) * 24, (W93 - D93) * 24), 24), 2) & " ชั่วโมง" -> 0.01 วัน 0.17 ชั่วโมง
A94: 93 | C94: ไลน์ | D94: 45552.453 | E94: =UPPER(LEFT(F94,3))&TEXT(COUNTA($F$2:F94),"000000") -> TRU000093 | F94: TRUE | G94: True Branding Shop CP Tower | K94: จอด้านหลังเคาเตอร์ไม่ติด | M94: YES | N94: แนะนำ | O94: ยกเลิก | P94: โมชิ | S94: เนื่องจากจอนี้ทาง DR ไม่ได้ดูแล | U94: Module | Y94: =ROUND(IF(ISBLANK(W94), (NOW() - D94) * 24 / 24, (W94 - D94) * 24 / 24), 2) & " วัน " & ROUND(MOD(IF(ISBLANK(W94), (NOW() - D94) * 24, (W94 - D94) * 24), 24), 2) & " ชั่วโมง" -> 713.97 วัน 23.17 ชั่วโมง
A95: 94 | C95: ไลน์ | D95: 45552.453 | E95: =UPPER(LEFT(F95,3))&TEXT(COUNTA($F$2:F95),"000000") -> TRU000094 | F95: TRUE | G95: True shop Seacon Square | I95: Oo RM | J95: 0891339997 | K95: จอทีวี Apple Sheep ซ้ายมือ ยังไม่ขึ้นสื่อ Apple Sheep | M95: YES | N95: รีโมท | O95: เรียบร้อยปกติ | P95: โมชิ | T95: แก้ไขสื่อเรียบร้อย | U95: แก้ไขสื่อ | W95: 45552.479 | Y95: =ROUND(IF(ISBLANK(W95), (NOW() - D95) * 24 / 24, (W95 - D95) * 24 / 24), 2) & " วัน " & ROUND(MOD(IF(ISBLANK(W95), (NOW() - D95) * 24, (W95 - D95) * 24), 24), 2) & " ชั่วโมง" -> 0.03 วัน 0.63 ชั่วโมง
A96: 95 | B96: 7346609 | C96: ไลน์ | D96: 45552.48 | E96: =UPPER(LEFT(F96,3))&TEXT(COUNTA($F$2:F96),"000000") -> TRU000095 | F96: TRUE | G96: True Shop Central Rama 3 | K96: จอ LED Wall จอไม่โชว์สื่อ วีโว่ v 40 | M96: YES | N96: รีโมท | O96: เรียบร้อยปกติ | P96: โมชิ | T96: แก้ไขสื่อเรียบร้อย | U96: แก้ไขสื่อ | W96: 45553.333 | Y96: =ROUND(IF(ISBLANK(W96), (NOW() - D96) * 24 / 24, (W96 - D96) * 24 / 24), 2) & " วัน " & ROUND(MOD(IF(ISBLANK(W96), (NOW() - D96) * 24, (W96 - D96) * 24), 24), 2) & " ชั่วโมง" -> 0.85 วัน 20.48 ชั่วโมง | AB96: TR0094
A97: 96 | C97: ไลน์ | D97: 45552.581 | E97: =UPPER(LEFT(F97,3))&TEXT(COUNTA($F$2:F97),"000000") -> TRU000096 | F97: TRUE | G97: เดอะมอลล์ บางกะปิ | I97: คุณราตรี | J97: 0863453555 | K97: จอสลับกัน | M97: YES | N97: รีโมท | O97: เรียบร้อยปกติ | P97: โมชิ | T97: แก้ไขสื่อเรียบร้อย | U97: แก้ไขสื่อ | W97: 45553.333 | Y97: =ROUND(IF(ISBLANK(W97), (NOW() - D97) * 24 / 24, (W97 - D97) * 24 / 24), 2) & " วัน " & ROUND(MOD(IF(ISBLANK(W97), (NOW() - D97) * 24, (W97 - D97) * 24), 24), 2) & " ชั่วโมง" -> 0.75 วัน 18.05 ชั่วโมง | AB97: TR0095
A98: 97 | C98: ไลน์ | D98: 45555.333 | E98: =UPPER(LEFT(F98,3))&TEXT(COUNTA($F$2:F98),"000000") -> TRU000097 | F98: TRUE | G98: สำนักงานใหญ่ | K98: เพิ่มสื่อ iPhone16 & iPhone16 Pro Launch ขอให้ขึ้นสื่อวันที่ 20/9/2024 เวลา 8:00 | M98: YES | N98: รีโมท | O98: เรียบร้อยปกติ | P98: โมชิ | S98: จอออนไลน์ในระบบ | T98: สื่ออัพเดทเรียบร้อย | U98: อัพเดทสื่อ | W98: 45555.708 | Y98: =ROUND(IF(ISBLANK(W98), (NOW() - D98) * 24 / 24, (W98 - D98) * 24 / 24), 2) & " วัน " & ROUND(MOD(IF(ISBLANK(W98), (NOW() - D98) * 24, (W98 - D98) * 24), 24), 2) & " ชั่วโมง" -> 0.38 วัน 9 ชั่วโมง | AA98: A. Highlight Campaign -Co Brand (ตามลิสสาขาที่มี) ------------------------------------- B. Commercial Campaign -True Coffee (TS Mega Bangna) -True ID Promote Thai League (ตามลิสสาขาที่มี) (13 Aug 2024-31 May 2025) -TVS NOW-EPL Sep2024 -TVS-EPL Sep2024 -True Online -True5G Postpaid (1/9/2024-31/10/2024)(ตามลิสสาขาที่มี) -iPhone16 Launch (ตามลิสสาขาที่มี) New!! -iPhone16 Pro Launch (ตามลิสสาขาที่มี) New!! -Huawei Matepad SE11 (ตามลิสสาขาที่มี) -Realme 12X exclusive TRUE DTAC -VIVO V40 (New!!!) -Samsung Flip 6 Fold 6 -OPPO Reno 12 Link สื่อใหม่ LED : iPhone16 Launch (20 Sep 08.00 น. - 31 Oct'24) https://drive.google.com/drive/folders/1yzbaOw47XBJ9h6BkpqgfvVWtqSLchiN8?usp=sharing LED : iPhone16 Pro Launch (20 Sep 08.00 น. - 31 Oct'24) https://drive.google.com/drive/folders/19OVAvdjGPyEEk6MjET2yQkngKYojCN6T?usp=sharing
A99: 98 | C99: ไลน์ | D99: 45552.625 | E99: =UPPER(LEFT(F99,3))&TEXT(COUNTA($F$2:F99),"000000") -> TRU000098 | F99: TRUE | G99: เอมคอลเทีย | I99: คุณหนึ่ง | J99: 0955049009 | K99: จอสลับกัน | M99: YES | N99: รีโมท | O99: เรียบร้อยปกติ | P99: โมชิ | T99: แก้ไขสื่อเรียบร้อย | U99: แก้ไขสื่อ | W99: 45553.333 | Y99: =ROUND(IF(ISBLANK(W99), (NOW() - D99) * 24 / 24, (W99 - D99) * 24 / 24), 2) & " วัน " & ROUND(MOD(IF(ISBLANK(W99), (NOW() - D99) * 24, (W99 - D99) * 24), 24), 2) & " ชั่วโมง" -> 0.71 วัน 17 ชั่วโมง | AB99: TR0097
A100: 99 | C100: ไลน์ | D100: 45552.646 | E100: =UPPER(LEFT(F100,3))&TEXT(COUNTA($F$2:F100),"000000") -> KAW000099 | F100: Kawasaki | G100: TOUGH CAFE ทัฟ คาเฟ่ | I100: คุณนัท | J100: 0878840922 | K100: จอไม่ขึ้นสื่อ มีข้อความ No Program 1.จอทัชกรีนไม่ได้ 2.เปลี่ยนสื่อไม่ได้ | M100: YES | N100: แก้ไขหน้างาน | O100: เรียบร้อยปกติ | P100: โมชิ | S100: 1.จอที่อยู่กับลูกค้าเป็นจอ ทรัชกรีน 1 ตัว ไม่ทรัชกรีน 1 ตัวครับ 2.ลูกค้าไม่ได้เชื่อมต่อ WiFi ครับ | T100: 1.ตรวจเช็คสาย USB ของจอทรัชกรีน พบว่า สาย USB หลุดครับ 2.เชื่อมต่อ WiFi และ พี่หนูเล็กยิงสื่อขึ้นให้ | U100: Sending | W100: 45553.586 | Y100: =ROUND(IF(ISBLANK(W100), (NOW() - D100) * 24 / 24, (W100 - D100) * 24 / 24), 2) & " วัน " & ROUND(MOD(IF(ISBLANK(W100), (NOW() - D100) * 24, (W100 - D100) * 24), 24), 2) & " ชั่วโมง" -> 0.94 วัน 22.57 ชั่วโมง | AB100: KA0098
...

Sheet ใบงานช่าง
F2: SERVICE REPORT | I2: หัวบริษัท
B4: ชื่องาน: | C4: =VLOOKUP(G6,DataServiceDR!E:AB,2,0) -> TRUE | D4: =VLOOKUP(G6,DataServiceDR!E:V,3,0) -> TS Terminal 21 Pattaya | F4: วันที่นัดหมาย: | G4: =VLOOKUP(G6,DataServiceDR!E:AB,13,0) -> 0
B5: ชื่อลูกค้า: | C5: =VLOOKUP(G6,DataServiceDR!E:AB,5,0) -> 0 | F5: เบอร์โทรติดต่อลูกค้า: | G5: =VLOOKUP(G6,DataServiceDR!E:AB,6,0) -> 0
B6: ช่องทางการแจ้งซ่อม: | F6: เลขที่ติดตาม: | G6: TRU000458
B8: อาการที่ได้รับแจ้ง: | D8: =VLOOKUP(G6,DataServiceDR!E:AB,7,0) -> งานขึ้นสื่อ ทรู สื่อ Apple Sheep เพิ่มเติมจาก
B9: =VLOOKUP(G6,DataServiceDR!E:AB,15,0) -> อัพสื่อเพิ่มเติมเ
B12: รูปอาการ : | F12: ผลการตรวจสอบ:
K13: Person In Charge
K14: Company:Bangkok Metro Networks Limited
K15: Item | L15: Thai Name | M15: Nick Name | N15: English Name | O15: Badge ID NO | P15: ประเภทบัตร | Q15: Expiry Date (PIC) | R15: Expiry Date (APOSTLE)
K16: 1 | L16: นายธเนศ ประจำแท่น | M16: ฟู | N16: Mr.Thanet Prachamthan | O16: BMN-P1221 | P16: PIC(HI,CE) | Q16: 24776 | R16: DR
F17: วิธีแก้ไข: | K17: 2 | L17: นายวีรชยน สมร | M17: จ่อย | N17: mr.Virachon Som | O17: BMN-P1218 | P17: PIC(HI,CE) | Q17: 24776 | R17: DR
K18: 3 | L18: นายวัฒนชัย อ่อนไธสง | M18: ศักดิ์ | N18: Mr.Wattananchai Onthaisong | O18: BMN-P1394 | P18: PIC(HI,CE) | Q18: 24776 | R18: DR
K19: 4 | L19: นายสามารถ ยาวิราช | M19: เหน่ง | N19: Mr.Samart Yawirach | O19: BMN-P1935 | P19: PIC(HI,CE,SCAF) | Q19: 24776 | R19: DR
K20: 5 | L20: ธงชัย ทองนิยม | N20: Mr.Thongchai thongniyom | O20: BMN-P1936 | P20: PIC(HI,CE,SCAF) | Q20: 24776 | R20: IDIO
K21: 6 | L21: นายวินัย สุโพธิ์ | N21: Mr.Vinai Supho | O21: BMN-P1937 | P21: PIC(HI,CE,SCAF) | Q21: 24776 | R21: IDIO
F22: ผลการแก้ไข: | K22: 7 | L22: นายวาฤทธิ์ แแก้วพิลส | N22: Mr.Waarit Keawpila | O22: BMN-P1938 | P22: PIC | Q22: 24411 | R22: IDIO | S22: รออบรม
K23: 8 | L23: นายศรายุทธ์ บางต่าย | N23: Mr.Sarayut Bangtai | O23: BMN-P1939 | P23: PIC | Q23: 24776 | R23: IDIO
K24: 9 | L24: นายนัทธพงส์ หมื่นศรี | N24: Mr.Nuttapong Muensri | O24: BMN-P1940 | P24: PIC | Q24: 24776 | R24: IDIO
L25: นายอติชาติ สอนโก่ย | N25: Mr.Atchart Sonkoi | O25: BMN-P1941 | P25: PIC | Q25: 24411 | R25: IDIO | S25: รออบรม
B26: รายชื่อช่าง: | C26: =VLOOKUP(G6,DataServiceDR!E:V,12,0) -> 0 | K26: 11 | L26: นายเกษม ประจำแท่น | M26: เตอร์ | N26: Mr.kasem Prachamthan | O26: BMN-P1948 | P26: PIC(HI,CE,SCAF) | Q26: 24776 | R26: DR
K27: 12 | L27: นายอนุวัต พ่วงชู | N27: Mr.Anuwat Poungchu | O27: BMN-P2054 | P27: PIC | Q27: 25142 | R27: IDIO
B28: ข้อเสนอแนะ: | K28: 13 | L28: นายไตรรัตน์ ปีกลาง | M28: นิค | N28: Mr.Trairat Peklang | O28: BMN-P2074 | P28: PIC(HI,CE,SCAF) | Q28: 25142 | R28: DR | S28: เพิ่มเปิดฝ้า
K29: 14 | L29: นายปรีชา ภูตานันท์ | M29: ชา | N29: Mr.Peecha Phootanan | O29: BMN-P2145 | P29: PIC | Q29: 24776 | R29: DR
L31: นายชินาธิป สุขธูป.jpg | M31: เณน
L32: นายปรีชา ภูตานันท์.jpg | M32: ชาสลิม
C33: ลงชื่อ | F33: ลงชื่อ | L33: นายณัฐวุฒิ อรรถประจง.jpg | M33: โอ๋
L34: นายสามารถ ยาวิราช.jpg | M34: เหน่ง 0625937779
B35: (..................................................................) | F35: (..................................................................) | L35: นายสุเมธ อะวะรัมย์.jpg | M35: แบงค์
C36: ช่างตรวจสอบแก้ไข | F36: ผู้ตรวจรับงาน | L36: นายเกรียงไกร นักธรรม.jpg | M36: นุ๊ก
L37: นายวุฒิพงษ์ สีใส.jpg | M37: มาร์ค
L38: นายบัญชา ทองโสม.jpg | M38: เอ้

Sheet Service แจ้งไลน์
D1: 1 | E1: 2 | F1: 3 | G1: 4 | H1: 5 | I1: 6 | J1: 7 | K1: 8 | L1: 9 | M1: 10 | N1: 11 | O1: 12 | P1: 13 | Q1: 14 | R1: 15 | S1: 16 | T1: 17 | U1: 18 | V1: 19 | W1: 20
E2: ข้อมูลลูกค้า | J2: ข้อมูลสินค้า | L2: การดำเนินการ | O2: รายละเอียดข้อมูล | Q2: วันเวลานัดหมาย
A3: Ref. | B3: จาก | C3: วันเวลาที่แจ้ง | D3: Tk NO. | E3: ลูกค้า | F3: สถานที่/สาขา | G3: ผู้ติดต่อ | H3: เบอร์โทร | I3: ข้อมูลการรับแจ้ง | J3: สินค้า/บริการ | K3: เงือนไข MA | L3: ลักษณะงาน | M3: สถานะงาน | N3: ผู้ดำเนินการ | O3: ผลการตรวจสอบ | P3: วิธีแก้ไข | Q3: วันเวลาเริ่ม | R3: วันเวลาสิ้นสุด | S3: วันเวลาเสร็จ | T3: วัน/ชั่วโมง ที่ใช้ | U3: หมายเหตุ | V3: ทะเบียนรถ | W3: ไฟล์
A5: 1.แจ้งเปิดเคสในกลุ่มลูกค้า
A6: ขออภัยในความไม่สะดวกที่เกิดขึ้น
A7: ทางทีมงานขอรับเรื่องไว้และรีบดำเนินการให้ครับ
A8: ขออนุญาตแจ้งเลขติดตามงาน: | B8: MA0210
A9: ลูกค้า: | B9: =VLOOKUP(B8,DataServiceDR!E:Y,2,0) -> #N/A
A10: สถานที่/สาขา: | B10: =VLOOKUP(B8,DataServiceDR!E:Y,3,0) -> #N/A
A11: ผู้ติดต่อ: | B11: =VLOOKUP(B8,DataServiceDR!E:Y,4,0) -> #N/A
A12: เบอร์โทร: | B12: =VLOOKUP(B8,DataServiceDR!E:Y,5,0) -> #N/A
A13: ข้อมูลการรับแจ้ง: | B13: =VLOOKUP(B8,DataServiceDR!E:Y,6,0) -> #N/A
A14: สถานะงาน: | B14: =VLOOKUP(B8,DataServiceDR!E:Y,10,0) -> #N/A
A15: @ลูกค้า
A17: 2.แจ้งงานส่งต่อในกลุ่ม Digital Signage Operation
A18: ขออนุญาตแจ้งเลขติดตามงาน: | B18: =B8 -> MA0210
A19: ลูกค้า: | B19: =VLOOKUP(B18,DataServiceDR!E:Y,2,0) -> #N/A
A20: สถานที่/สาขา: ไอคอนสยาม | B20: =VLOOKUP(B18,DataServiceDR!E:Y,3,0) -> #N/A
A21: ผู้ติดต่อ: | B21: =VLOOKUP(B18,DataServiceDR!E:Y,4,0) -> #N/A
A22: เบอร์โทร: | B22: =VLOOKUP(B18,DataServiceDR!E:Y,5,0) -> #N/A
A23: ข้อมูลการรับแจ้ง: | B23: =VLOOKUP(B18,DataServiceDR!E:Y,6,0) -> #N/A
A24: รายละเอียดข้อมูล: ex.เนื่องจากหมดอายุประกันแล้วรบกวนทำใบเสนอราคารายการดังนี้ | B24: =VLOOKUP(B18,DataServiceDR!E:Y,12,0) -> #N/A
A25: สถานะงาน: | B25: =VLOOKUP(B8,DataServiceDR!E:Y,10,0) -> #N/A
A26: @S🦋 @DR Sale Coordinator @Mac @j-pan & j-day
A28: 3.แจ้งงานส่งต่อกลุ่ม ขอ PR สั่งซื้อ
A29: ขออนุญาตแจ้งเลขติดตามงาน: | B29: =B8 -> MA0210
A30: ลูกค้า: | B30: =VLOOKUP(B18,DataServiceDR!E:Y,2,0) -> #N/A
A31: สถานที่/สาขา: | B31: =VLOOKUP(B29,DataServiceDR!E:Y,3,0) -> #N/A
A32: ผู้ติดต่อ: | B32: =VLOOKUP(B29,DataServiceDR!E:Y,4,0) -> #N/A
A33: เบอร์โทร: | B33: =VLOOKUP(B29,DataServiceDR!E:Y,5,0) -> #N/A
A34: ข้อมูลการรับแจ้ง: | B34: =VLOOKUP(B18,DataServiceDR!E:Y,6,0) -> #N/A
A35: รายละเอียดข้อมูล: | B35: =VLOOKUP(B18,DataServiceDR!E:Y,12,0) -> #N/A
A36: สถานะงาน: | B36: =VLOOKUP(B18,DataServiceDR!E:Y,10,0) -> #N/A
A37: @DR-จัดซื้อ (เรย์) @DR จัดซื้อ (ทราย) @Lyn🐷Tiney🐰Thamma
A39: 4.แจ้งขอคิวช่างเข้าดำเนินการ ในกลุ่มDRปรึกษาการเข้างาน
A40: ขออนุญาตแจ้งเลขติดตามงาน: | B40: =B8 -> MA0210
A41: ลูกค้า: | B41: =VLOOKUP(B18,DataServiceDR!E:Y,2,0) -> #N/A
A42: สถานที่/สาขา: | B42: =VLOOKUP(B18,DataServiceDR!E:Y,3,0) -> #N/A
A43: ข้อมูลการรับแจ้ง: | B43: =VLOOKUP(B18,DataServiceDR!E:Y,6,0) -> #N/A
A44: สถานะงาน: | B44: =VLOOKUP(B18,DataServiceDR!E:Y,10,0) -> #N/A
A45: วันเวลานัดหมายเริ่มต้น | B45: =VLOOKUP(B18,DataServiceDR!E:Y,14,0) -> #N/A
A46: วันเวลานัดหมายสิ้นสุด | B46: =VLOOKUP(B18,DataServiceDR!E:Y,15,0) -> #N/A
A47: รายละเอียด: | B47: =VLOOKUP(B18,DataServiceDR!E:Y,12,0) -> #N/A
A48: @Manapol Yimfoi @ball
A50: 5.แจ้งนัดหมายขอเข้าพื้นที่ ในกลุ่มลูกค้า
A51: เรียน ผู้ที่เกี่ยวข้อง
A52: *ขออนุญาตนัดหมายเข้าพื้นที่หน้างาน: | B52: =B8 -> MA0210
A53: ลูกค้า: | B53: =VLOOKUP(B18,DataServiceDR!E:Y,2,0) -> #N/A
A54: สถานที่/สาขา: ไอคอนสยาม | B54: =VLOOKUP(B18,DataServiceDR!E:Y,3,0) -> #N/A
A55: สถานะงาน: | B55: กำลังดำเนินการ
A56: ข้อมูลการรับแจ้ง: | B56: =VLOOKUP(B18,DataServiceDR!E:Y,6,0) -> #N/A
A57: วันเวลานัดหมายเริ่มต้น | B57: =VLOOKUP(B18,DataServiceDR!E:Y,14,0) -> #N/A
A58: วันเวลานัดหมายสิ้นสุด | B58: =VLOOKUP(B18,DataServiceDR!E:Y,15,0) -> #N/A
A59: ขอแจ้งรายชื่อช่างเข้างาน : | B59: =VLOOKUP(B18,DataServiceDR!E:Y,11,0) -> #N/A | C59: ชื่อเต็ม
A60: ทะเบียนรถ: | B60: =VLOOKUP(B18,DataServiceDR!E:Y,19,0) -> #N/A
A61: หมายเหต: | B61: =VLOOKUP(B18,DataServiceDR!E:Y,18,0) -> #N/A
A62: สถานะงาน: | B62: =VLOOKUP(B18,DataServiceDR!E:Y,10,0) -> #N/A
A63: @ลูกค้า
A65: 6.แจ้งปิดงานในกลุ่มลูกค้า
A66: ขออนุญาตแจ้งเลขติดตามงาน: | B66: =B8 -> MA0210
A67: ลูกค้า: | B67: =VLOOKUP(B8,DataServiceDR!E:Y,2,0) -> #N/A
A68: สถานที่/สาขา: | B68: =VLOOKUP(B8,DataServiceDR!E:Y,3,0) -> #N/A
A69: ข้อมูลการรับแจ้ง: | B69: =VLOOKUP(B8,DataServiceDR!E:Y,6,0) -> #N/A
A70: ผลการตรวจสอบ: | B70: =VLOOKUP(B8,DataServiceDR!E:Y,12,0) -> #N/A
A71: วิธีแก้ไข: | B71: =VLOOKUP(B8,DataServiceDR!E:Y,13,0) -> #N/A
A72: สถานะงาน: | B72: =VLOOKUP(B8,DataServiceDR!E:Y,10,0) -> #N/A
A73: ขอขอบพระคุณอีกครั้งที่ไว้วางใจใช้บริการจากเรา
A74: หากมีข้อสงสัยหรือต้องการข้อมูลเพิ่มเติม
A75: กรุณาติดต่อ 0825255238
A76: คุณหนูเล็ก,คุณโจ๊ก
A77: @ลูกค้า
